{"id":"2026-04-21-dagen-med-di","feed":"dagen-med-di","title":"Avanza inleder expansion: \"Naturligt första steg\"","pub_date":"2026-04-21","overall_sentiment":"neutral","summary_md":"# Avanza inleder expansion: \"Naturligt första steg\"\n\n**Feed**: dagen-med-di  \n**Published**: 2026-04-21  \n**Market Sentiment**: Neutral\n\n## Summary\n\nTwo Dagen med DI episodes from 2026-04-21:\n\n**Investor AB Q1** (Christian Sederholm, CEO): NAV +3%, total return +7% vs OMXS30 -1%.\nPortfolio companies navigating geopolitical disruptions — logistics headwinds visible but\nno significant P&L impact yet. Investor bought Atlas Copco and EQT at what it considers\nattractive levels; sold some SEB to comply with regulatory ownership limits. CEO warns\ncost inflation from Mideast conflict will show in P&Ls if conflict extends further.\n\n**Avanza Q1 record results**: 55,000 new customers (vs ~40K late 2024), net inflow 16.5B SEK,\nrecord quarterly profit. Denmark expansion announced for H2 2027 at 120–150M SEK cost.\nCEO: building new platform rather than adapting Swedish one; AI-driven development cost\nreduction makes this viable. Stock fell on Denmark news (market wanted Germany?).\n\nBoth companies are large-cap; no Swedish small/mid-cap universe signals.\n\n## Recommendations\n\n_No signals for universe stocks in this episode._\n","signals":[],"prices":{}}