[{"timestamp":"2026-06-10T14:30:03.357118+00:00","T5":705.0,"T8":94.0,"T9":1.0,"t9_branch_count_offmain":0.0,"t5_bearish_sell_today":42.0,"t5_audit_dissent_coverage":0.0,"t5_expert_panel_coverage_7d":0.0,"T6":0.0323,"t6_valuation_coverage":0.9923,"T7":0.9677,"t8_universe_coverage":94.0,"t8_local_bars_coverage":1.0,"T4":0.0,"t4_avg_holding_days_closed":27.3333,"T2":0.0,"t7_t7_earnings_calendar_freshness":1.0,"VAL":0.0,"t9_backtest_runs_last_28d":4.0,"t9_weekly_reports_with_scorecard":1.0,"t5_t5_weekly_scorecard_present":0.0,"t9_podcast_transcript_validity":0.9118,"t6_annual_report_corpus_tokens":0.2009,"t9_qualitative_signal_coverage":0.5262,"t5_conviction_high_hit_rate_13w":0.0,"t5_conviction_medium_hit_rate_13w":0.0,"t5_conviction_low_hit_rate_13w":0.0,"ib_source_share":0.0323,"ib_field_coverage_avg":10.3333,"equity_curve_points_30d":0,"weekly_issues_report_present":true,"open_p0_issues":0},{"timestamp":"2026-06-05T15:35:33.017137+00:00","T5":1217.0,"T8":94.0,"T9":1.0,"t9_branch_count_offmain":0.0,"t5_bearish_sell_today":39.0,"t5_audit_dissent_coverage":0.0,"t5_expert_panel_coverage_7d":0.0,"T6":0.0323,"t6_valuation_coverage":0.9955,"T7":0.9677,"t8_universe_coverage":94.0,"t8_local_bars_coverage":1.0,"T4":0.0,"t4_avg_holding_days_closed":27.3333,"T2":0.0,"t7_t7_earnings_calendar_freshness":1.0,"VAL":0.0,"t9_backtest_runs_last_28d":5.0,"t9_weekly_reports_with_scorecard":1.0,"t5_t5_weekly_scorecard_present":1.0,"t9_podcast_transcript_validity":0.9118,"t6_annual_report_corpus_tokens":0.2009,"t9_qualitative_signal_coverage":0.4906,"t5_conviction_high_hit_rate_13w":0.0,"t5_conviction_medium_hit_rate_13w":0.0,"t5_conviction_low_hit_rate_13w":0.0,"ib_source_share":0.0323,"ib_field_coverage_avg":10.3333,"equity_curve_points_30d":0,"weekly_issues_report_present":true,"open_p0_issues":0},{"timestamp":"2026-06-11T13:30:03.103832+00:00","T5":666.0,"T8":94.0,"T9":1.0,"t9_branch_count_offmain":0.0,"t5_bearish_sell_today":4.0,"t5_audit_dissent_coverage":0.0,"t5_category_score_coverage":0.0,"t5_expert_panel_coverage_7d":0.0,"T6":0.0323,"t6_valuation_coverage":0.9863,"T7":0.9677,"t8_universe_coverage":96.0,"t8_local_bars_coverage":0.9583,"T4":0.0,"t4_avg_holding_days_closed":34.5833,"T2":0.0,"t7_t7_earnings_calendar_freshness":0.9583,"VAL":0.0,"t9_backtest_runs_last_28d":4.0,"t9_weekly_reports_with_scorecard":1.0,"t5_t5_weekly_scorecard_present":0.0,"t9_podcast_transcript_validity":0.9123,"t6_annual_report_corpus_tokens":0.2948,"t9_qualitative_signal_coverage":0.5556,"t5_conviction_high_hit_rate_13w":0.0,"t5_conviction_medium_hit_rate_13w":0.0,"t5_conviction_low_hit_rate_13w":0.0,"ib_source_share":0.0323,"ib_field_coverage_avg":10.3333,"equity_curve_points_30d":0,"weekly_issues_report_present":true,"open_p0_issues":0},{"timestamp":"2026-06-11T14:30:53.922954+00:00","T5":666.0,"T8":94.0,"T9":1.0,"t9_branch_count_offmain":0.0,"t5_bearish_sell_today":4.0,"t5_audit_dissent_coverage":0.0,"t5_category_score_coverage":0.0,"t5_expert_panel_coverage_7d":0.0,"T6":0.0323,"t6_valuation_coverage":0.9863,"T7":0.9677,"t8_universe_coverage":96.0,"t8_local_bars_coverage":0.9583,"T4":0.0,"t4_avg_holding_days_closed":34.5833,"T2":0.0,"t7_t7_earnings_calendar_freshness":0.9583,"VAL":0.0,"t9_backtest_runs_last_28d":4.0,"t9_weekly_reports_with_scorecard":1.0,"t5_t5_weekly_scorecard_present":0.0,"t9_podcast_transcript_validity":0.9138,"t6_annual_report_corpus_tokens":0.2948,"t9_qualitative_signal_coverage":0.5556,"t5_conviction_high_hit_rate_13w":0.0,"t5_conviction_medium_hit_rate_13w":0.0,"t5_conviction_low_hit_rate_13w":0.0,"ib_source_share":0.0323,"ib_field_coverage_avg":10.3333,"equity_curve_points_30d":0,"weekly_issues_report_present":true,"open_p0_issues":0},{"timestamp":"2026-06-11T18:00:55.453135+00:00","T5":666.0,"T8":94.0,"T9":1.0,"t9_branch_count_offmain":0.0,"t5_bearish_sell_today":4.0,"t5_audit_dissent_coverage":0.0,"t5_category_score_coverage":0.0,"t5_expert_panel_coverage_7d":0.0,"T6":0.0323,"t6_valuation_coverage":0.9863,"T7":0.9677,"t8_universe_coverage":96.0,"t8_local_bars_coverage":0.9583,"T4":0.0,"t4_avg_holding_days_closed":34.5833,"T2":0.0,"t7_t7_earnings_calendar_freshness":0.9583,"VAL":0.0,"t9_backtest_runs_last_28d":4.0,"t9_weekly_reports_with_scorecard":1.0,"t5_t5_weekly_scorecard_present":0.0,"t9_podcast_transcript_validity":0.9138,"t6_annual_report_corpus_tokens":0.2948,"t9_qualitative_signal_coverage":0.5556,"t5_conviction_high_hit_rate_13w":0.0,"t5_conviction_medium_hit_rate_13w":0.0,"t5_conviction_low_hit_rate_13w":0.0,"ib_source_share":0.0323,"ib_field_coverage_avg":10.3333,"equity_curve_points_30d":0,"weekly_issues_report_present":true,"open_p0_issues":0},{"timestamp":"2026-06-11T23:00:53.792725+00:00","T5":666.0,"T8":94.0,"T9":1.0,"t9_branch_count_offmain":0.0,"t5_bearish_sell_today":4.0,"t5_audit_dissent_coverage":0.0,"t5_category_score_coverage":0.0,"t5_expert_panel_coverage_7d":0.0,"T6":0.97,"t6_valuation_coverage":0.9863,"T7":0.99,"t8_universe_coverage":96.0,"t8_local_bars_coverage":0.9583,"T4":0.0,"t4_avg_holding_days_closed":34.5833,"T10":1.0,"T2":0.0,"t7_t7_earnings_calendar_freshness":0.9583,"VAL":0.0,"t9_backtest_runs_last_28d":4.0,"t9_weekly_reports_with_scorecard":1.0,"t5_t5_weekly_scorecard_present":0.0,"t9_podcast_transcript_validity":0.9138,"t6_annual_report_corpus_tokens":0.3084,"t9_qualitative_signal_coverage":0.5556,"t5_conviction_high_hit_rate_13w":0.0,"t5_conviction_medium_hit_rate_13w":0.0,"t5_conviction_low_hit_rate_13w":0.0,"ib_source_share":0.97,"ib_field_coverage_avg":11.6186,"equity_curve_points_30d":0,"weekly_issues_report_present":true,"open_p0_issues":0},{"timestamp":"2026-06-12T00:30:02.216878+00:00","T5":666.0,"T8":0.0,"T9":0.0,"t9_branch_count_offmain":0.0,"t5_bearish_sell_today":0.0,"t5_audit_dissent_coverage":0.0,"t5_category_score_coverage":0.0,"t5_expert_panel_coverage_7d":0.0,"T6":0.97,"t6_valuation_coverage":0.9863,"T7":0.99,"t8_universe_coverage":96.0,"t8_local_bars_coverage":0.9583,"T4":0.0,"t4_avg_holding_days_closed":34.5833,"T10":1.0,"T2":0.0,"t7_t7_earnings_calendar_freshness":0.9583,"VAL":0.0,"t9_backtest_runs_last_28d":4.0,"t9_weekly_reports_with_scorecard":1.0,"t5_t5_weekly_scorecard_present":0.0,"t9_podcast_transcript_validity":0.9143,"t6_annual_report_corpus_tokens":0.3084,"t9_qualitative_signal_coverage":0.5556,"t5_conviction_high_hit_rate_13w":0.0,"t5_conviction_medium_hit_rate_13w":0.0,"t5_conviction_low_hit_rate_13w":0.0,"ib_source_share":0.97,"ib_field_coverage_avg":11.6186,"equity_curve_points_30d":0,"weekly_issues_report_present":true,"open_p0_issues":0},{"timestamp":"2026-06-12T04:30:53.717124+00:00","T5":666.0,"T8":0.0,"T9":0.0,"t9_branch_count_offmain":0.0,"t5_bearish_sell_today":0.0,"t5_audit_dissent_coverage":0.0,"t5_category_score_coverage":0.0,"t5_expert_panel_coverage_7d":0.0,"T6":0.97,"t6_valuation_coverage":0.9863,"T7":0.99,"t8_universe_coverage":96.0,"t8_local_bars_coverage":0.9583,"T4":0.0,"t4_avg_holding_days_closed":34.5833,"T10":1.0,"T2":0.0,"t7_t7_earnings_calendar_freshness":0.9583,"VAL":0.0,"t9_backtest_runs_last_28d":4.0,"t9_weekly_reports_with_scorecard":1.0,"t5_t5_weekly_scorecard_present":0.0,"t9_podcast_transcript_validity":0.9153,"t6_annual_report_corpus_tokens":0.3084,"t9_qualitative_signal_coverage":0.5556,"t5_conviction_high_hit_rate_13w":0.0,"t5_conviction_medium_hit_rate_13w":0.0,"t5_conviction_low_hit_rate_13w":0.0,"ib_source_share":0.97,"ib_field_coverage_avg":11.6186,"equity_curve_points_30d":0,"weekly_issues_report_present":true,"open_p0_issues":0},{"timestamp":"2026-06-12T07:30:53.632184+00:00","T5":669.0,"T8":96.0,"T9":0.9062,"t9_branch_count_offmain":0.0,"t5_bearish_sell_today":24.0,"t5_audit_dissent_coverage":0.0,"t5_category_score_coverage":0.13,"t5_expert_panel_coverage_7d":0.0,"T6":0.97,"t6_valuation_coverage":0.9908,"T7":0.99,"t8_universe_coverage":96.0,"t8_local_bars_coverage":1.0,"T4":0.0,"t4_avg_holding_days_closed":34.5833,"T10":1.0,"T2":0.0,"t7_t7_earnings_calendar_freshness":1.0,"VAL":0.0,"t9_backtest_runs_last_28d":4.0,"t9_weekly_reports_with_scorecard":1.0,"t5_t5_weekly_scorecard_present":0.0,"t9_podcast_transcript_validity":0.9153,"t6_annual_report_corpus_tokens":0.329,"t9_qualitative_signal_coverage":0.5561,"t5_conviction_high_hit_rate_13w":0.0,"t5_conviction_medium_hit_rate_13w":0.0,"t5_conviction_low_hit_rate_13w":0.0,"ib_source_share":0.97,"ib_field_coverage_avg":9.7629,"equity_curve_points_30d":0,"weekly_issues_report_present":true,"open_p0_issues":0},{"timestamp":"2026-06-12T12:00:53.885354+00:00","T5":675.0,"T8":96.0,"T9":0.9062,"t9_branch_count_offmain":0.0,"t5_bearish_sell_today":24.0,"t5_audit_dissent_coverage":0.0,"t5_category_score_coverage":0.1378,"t5_expert_panel_coverage_7d":0.0,"T6":0.97,"t6_valuation_coverage":0.9909,"T7":0.99,"t8_universe_coverage":96.0,"t8_local_bars_coverage":1.0,"T4":0.0,"t4_avg_holding_days_closed":34.5833,"T10":1.0,"T2":0.0,"t7_t7_earnings_calendar_freshness":1.0,"VAL":0.0,"t9_backtest_runs_last_28d":4.0,"t9_weekly_reports_with_scorecard":1.0,"t5_t5_weekly_scorecard_present":0.0,"t9_podcast_transcript_validity":0.9153,"t6_annual_report_corpus_tokens":0.3365,"t9_qualitative_signal_coverage":0.5511,"t5_conviction_high_hit_rate_13w":0.0,"t5_conviction_medium_hit_rate_13w":0.0,"t5_conviction_low_hit_rate_13w":0.0,"ib_source_share":0.97,"ib_field_coverage_avg":9.7629,"equity_curve_points_30d":0,"weekly_issues_report_present":true,"open_p0_issues":0},{"timestamp":"2026-06-12T13:30:55.487486+00:00","T5":675.0,"T8":96.0,"T9":0.9062,"t9_branch_count_offmain":0.0,"t5_bearish_sell_today":24.0,"t5_audit_dissent_coverage":0.0,"t5_category_score_coverage":0.1378,"t5_expert_panel_coverage_7d":0.0,"T6":0.97,"t6_valuation_coverage":0.9909,"T7":0.99,"t8_universe_coverage":96.0,"t8_local_bars_coverage":1.0,"T4":0.0,"t4_avg_holding_days_closed":34.5833,"T10":1.0,"T2":0.0,"t7_t7_earnings_calendar_freshness":1.0,"VAL":0.0,"t9_backtest_runs_last_28d":4.0,"t9_weekly_reports_with_scorecard":1.0,"t5_t5_weekly_scorecard_present":0.0,"t9_podcast_transcript_validity":0.9153,"t6_annual_report_corpus_tokens":0.3365,"t9_qualitative_signal_coverage":0.5511,"t5_conviction_high_hit_rate_13w":0.0,"t5_conviction_medium_hit_rate_13w":0.0,"t5_conviction_low_hit_rate_13w":0.0,"ib_source_share":0.97,"ib_field_coverage_avg":9.7629,"equity_curve_points_30d":0,"weekly_issues_report_present":true,"open_p0_issues":0},{"timestamp":"2026-06-12T14:30:55.485697+00:00","T5":675.0,"T8":96.0,"T9":0.9062,"t9_branch_count_offmain":0.0,"t5_bearish_sell_today":24.0,"t5_audit_dissent_coverage":0.0,"t5_category_score_coverage":0.1378,"t5_expert_panel_coverage_7d":0.0,"T6":0.97,"t6_valuation_coverage":0.9909,"T7":0.99,"t8_universe_coverage":96.0,"t8_local_bars_coverage":1.0,"T4":0.0,"t4_avg_holding_days_closed":34.5833,"T10":1.0,"T2":0.0,"t7_t7_earnings_calendar_freshness":1.0,"VAL":0.0,"t9_backtest_runs_last_28d":4.0,"t9_weekly_reports_with_scorecard":1.0,"t5_t5_weekly_scorecard_present":0.0,"t9_podcast_transcript_validity":0.9153,"t6_annual_report_corpus_tokens":0.3365,"t9_qualitative_signal_coverage":0.5511,"t5_conviction_high_hit_rate_13w":0.0,"t5_conviction_medium_hit_rate_13w":0.0,"t5_conviction_low_hit_rate_13w":0.0,"ib_source_share":0.97,"ib_field_coverage_avg":9.7629,"equity_curve_points_30d":0,"weekly_issues_report_present":true,"open_p0_issues":0},{"timestamp":"2026-06-12T18:00:55.464390+00:00","T5":675.0,"T8":96.0,"T9":0.9062,"t9_branch_count_offmain":0.0,"t5_bearish_sell_today":24.0,"t5_audit_dissent_coverage":0.0,"t5_category_score_coverage":0.1378,"t5_expert_panel_coverage_7d":0.0,"T6":0.97,"t6_valuation_coverage":0.9909,"T7":0.99,"t8_universe_coverage":96.0,"t8_local_bars_coverage":1.0,"T4":0.0,"t4_avg_holding_days_closed":34.5833,"T10":1.0,"T2":0.0,"t7_t7_earnings_calendar_freshness":1.0,"VAL":0.0,"t9_backtest_runs_last_28d":4.0,"t9_weekly_reports_with_scorecard":1.0,"t5_t5_weekly_scorecard_present":0.0,"t9_podcast_transcript_validity":0.9153,"t6_annual_report_corpus_tokens":0.3365,"t9_qualitative_signal_coverage":0.5511,"t5_conviction_high_hit_rate_13w":0.0,"t5_conviction_medium_hit_rate_13w":0.0,"t5_conviction_low_hit_rate_13w":0.0,"ib_source_share":0.97,"ib_field_coverage_avg":9.7629,"equity_curve_points_30d":0,"weekly_issues_report_present":true,"open_p0_issues":0},{"timestamp":"2026-06-12T23:00:55.358488+00:00","T5":675.0,"T8":96.0,"T9":0.9062,"t9_branch_count_offmain":0.0,"t5_bearish_sell_today":24.0,"t5_audit_dissent_coverage":0.0,"t5_category_score_coverage":0.1378,"t5_expert_panel_coverage_7d":0.0,"T6":0.97,"t6_valuation_coverage":0.9909,"T7":0.97,"t8_universe_coverage":96.0,"t8_local_bars_coverage":1.0,"T4":0.0,"t4_avg_holding_days_closed":34.5833,"T10":1.0,"T2":0.0,"t7_t7_earnings_calendar_freshness":1.0,"VAL":0.0,"t9_backtest_runs_last_28d":4.0,"t9_weekly_reports_with_scorecard":1.0,"t5_t5_weekly_scorecard_present":0.0,"t9_podcast_transcript_validity":0.9153,"t6_annual_report_corpus_tokens":0.3365,"t9_qualitative_signal_coverage":0.5511,"t5_conviction_high_hit_rate_13w":0.0,"t5_conviction_medium_hit_rate_13w":0.0,"t5_conviction_low_hit_rate_13w":0.0,"ib_source_share":0.97,"ib_field_coverage_avg":9.7629,"equity_curve_points_30d":0,"weekly_issues_report_present":true,"open_p0_issues":0},{"timestamp":"2026-06-13T00:30:02.396457+00:00","T5":675.0,"T8":0.0,"T9":0.0,"t9_branch_count_offmain":0.0,"t5_bearish_sell_today":0.0,"t5_audit_dissent_coverage":0.0,"t5_category_score_coverage":0.1378,"t5_expert_panel_coverage_7d":0.0,"T6":0.97,"t6_valuation_coverage":0.9909,"T7":0.96,"t8_universe_coverage":96.0,"t8_local_bars_coverage":1.0,"T4":0.0,"t4_avg_holding_days_closed":34.5833,"T10":1.0,"T2":0.0,"t7_t7_earnings_calendar_freshness":0.0417,"VAL":0.0,"t9_backtest_runs_last_28d":4.0,"t9_weekly_reports_with_scorecard":1.0,"t5_t5_weekly_scorecard_present":0.0,"t9_podcast_transcript_validity":0.9153,"t6_annual_report_corpus_tokens":0.3365,"t9_qualitative_signal_coverage":0.5511,"t5_conviction_high_hit_rate_13w":0.0,"t5_conviction_medium_hit_rate_13w":0.0,"t5_conviction_low_hit_rate_13w":0.0,"ib_source_share":0.97,"ib_field_coverage_avg":9.7629,"equity_curve_points_30d":0,"weekly_issues_report_present":true,"open_p0_issues":0},{"timestamp":"2026-06-13T04:30:53.739040+00:00","T5":675.0,"T8":0.0,"T9":0.0,"t9_branch_count_offmain":0.0,"t5_bearish_sell_today":0.0,"t5_audit_dissent_coverage":0.0,"t5_category_score_coverage":0.1378,"t5_expert_panel_coverage_7d":0.0,"T6":0.97,"t6_valuation_coverage":0.9909,"T7":0.96,"t8_universe_coverage":96.0,"t8_local_bars_coverage":1.0,"T4":0.0,"t4_avg_holding_days_closed":34.5833,"T10":1.0,"T2":0.0,"t7_t7_earnings_calendar_freshness":0.0417,"VAL":0.0,"t9_backtest_runs_last_28d":4.0,"t9_weekly_reports_with_scorecard":1.0,"t5_t5_weekly_scorecard_present":0.0,"t9_podcast_transcript_validity":0.9176,"t6_annual_report_corpus_tokens":0.3365,"t9_qualitative_signal_coverage":0.5511,"t5_conviction_high_hit_rate_13w":0.0,"t5_conviction_medium_hit_rate_13w":0.0,"t5_conviction_low_hit_rate_13w":0.0,"ib_source_share":0.97,"ib_field_coverage_avg":9.7629,"equity_curve_points_30d":0,"weekly_issues_report_present":true,"open_p0_issues":0},{"timestamp":"2026-06-13T07:30:02.891858+00:00","T5":582.0,"T8":0.0,"T9":0.0,"t9_branch_count_offmain":0.0,"t5_bearish_sell_today":0.0,"t5_audit_dissent_coverage":0.0,"t5_category_score_coverage":0.1598,"t5_expert_panel_coverage_7d":0.0,"T6":0.97,"t6_valuation_coverage":0.9894,"T7":0.03,"t8_universe_coverage":96.0,"t8_local_bars_coverage":1.0,"T4":0.0,"t4_avg_holding_days_closed":34.5833,"T10":1.0,"T2":0.0,"t7_t7_earnings_calendar_freshness":0.0417,"VAL":0.0,"t9_backtest_runs_last_28d":4.0,"t9_weekly_reports_with_scorecard":1.0,"t5_t5_weekly_scorecard_present":0.0,"t9_podcast_transcript_validity":0.9176,"t6_annual_report_corpus_tokens":0.3365,"t9_qualitative_signal_coverage":0.548,"t5_conviction_high_hit_rate_13w":0.0,"t5_conviction_medium_hit_rate_13w":0.0,"t5_conviction_low_hit_rate_13w":0.0,"ib_source_share":0.97,"ib_field_coverage_avg":9.7629,"equity_curve_points_30d":0,"weekly_issues_report_present":true,"open_p0_issues":0},{"timestamp":"2026-06-13T09:00:01.212285+00:00","T5":582.0,"T8":0.0,"T9":0.0,"t9_branch_count_offmain":0.0,"t5_bearish_sell_today":0.0,"t5_audit_dissent_coverage":0.0,"t5_category_score_coverage":0.1598,"t5_expert_panel_coverage_7d":0.0,"T6":0.97,"t6_valuation_coverage":0.9894,"T7":0.03,"t8_universe_coverage":96.0,"t8_local_bars_coverage":1.0,"T4":0.0,"t4_avg_holding_days_closed":34.5833,"T10":1.0,"T2":0.0,"t7_t7_earnings_calendar_freshness":0.0417,"VAL":0.0,"t9_backtest_runs_last_28d":4.0,"t9_weekly_reports_with_scorecard":1.0,"t5_t5_weekly_scorecard_present":0.0,"t9_podcast_transcript_validity":0.9176,"t6_annual_report_corpus_tokens":0.3365,"t9_qualitative_signal_coverage":0.548,"t5_conviction_high_hit_rate_13w":0.0,"t5_conviction_medium_hit_rate_13w":0.0,"t5_conviction_low_hit_rate_13w":0.0,"ib_source_share":0.97,"ib_field_coverage_avg":9.7629,"equity_curve_points_30d":0,"weekly_issues_report_present":true,"open_p0_issues":0},{"timestamp":"2026-06-13T12:00:02.702719+00:00","T5":582.0,"T8":0.0,"T9":0.0,"t9_branch_count_offmain":0.0,"t5_bearish_sell_today":0.0,"t5_audit_dissent_coverage":0.0,"t5_category_score_coverage":0.1598,"t5_expert_panel_coverage_7d":0.0,"T6":0.97,"t6_valuation_coverage":0.9894,"T7":0.03,"t8_universe_coverage":96.0,"t8_local_bars_coverage":1.0,"T4":0.0,"t4_avg_holding_days_closed":34.5833,"T10":1.0,"T2":0.0,"t7_t7_earnings_calendar_freshness":0.0417,"VAL":0.0,"t9_backtest_runs_last_28d":4.0,"t9_weekly_reports_with_scorecard":1.0,"t5_t5_weekly_scorecard_present":0.0,"t9_podcast_transcript_validity":0.9176,"t6_annual_report_corpus_tokens":0.3365,"t9_qualitative_signal_coverage":0.548,"t5_conviction_high_hit_rate_13w":0.0,"t5_conviction_medium_hit_rate_13w":0.0,"t5_conviction_low_hit_rate_13w":0.0,"ib_source_share":0.97,"ib_field_coverage_avg":9.7629,"equity_curve_points_30d":0,"weekly_issues_report_present":true,"open_p0_issues":0},{"timestamp":"2026-06-13T13:30:02.618183+00:00","T5":582.0,"T8":0.0,"T9":0.0,"t9_branch_count_offmain":0.0,"t5_bearish_sell_today":0.0,"t5_audit_dissent_coverage":0.0,"t5_category_score_coverage":0.1598,"t5_expert_panel_coverage_7d":0.0,"T6":0.97,"t6_valuation_coverage":0.9894,"T7":0.03,"t8_universe_coverage":96.0,"t8_local_bars_coverage":1.0,"T4":0.0,"t4_avg_holding_days_closed":34.5833,"T10":1.0,"T2":0.0,"t7_t7_earnings_calendar_freshness":0.0417,"VAL":0.0,"t9_backtest_runs_last_28d":4.0,"t9_weekly_reports_with_scorecard":1.0,"t5_t5_weekly_scorecard_present":0.0,"t9_podcast_transcript_validity":0.9176,"t6_annual_report_corpus_tokens":0.3365,"t9_qualitative_signal_coverage":0.548,"t5_conviction_high_hit_rate_13w":0.0,"t5_conviction_medium_hit_rate_13w":0.0,"t5_conviction_low_hit_rate_13w":0.0,"ib_source_share":0.97,"ib_field_coverage_avg":9.7629,"equity_curve_points_30d":0,"weekly_issues_report_present":true,"open_p0_issues":0},{"timestamp":"2026-06-13T14:30:02.867232+00:00","T5":582.0,"T8":0.0,"T9":0.0,"t9_branch_count_offmain":0.0,"t5_bearish_sell_today":0.0,"t5_audit_dissent_coverage":0.0,"t5_category_score_coverage":0.1598,"t5_expert_panel_coverage_7d":0.0,"T6":0.97,"t6_valuation_coverage":0.9894,"T7":0.03,"t8_universe_coverage":96.0,"t8_local_bars_coverage":1.0,"T4":0.0,"t4_avg_holding_days_closed":34.5833,"T10":1.0,"T2":0.0,"t7_t7_earnings_calendar_freshness":0.0417,"VAL":0.0,"t9_backtest_runs_last_28d":4.0,"t9_weekly_reports_with_scorecard":1.0,"t5_t5_weekly_scorecard_present":0.0,"t9_podcast_transcript_validity":0.9176,"t6_annual_report_corpus_tokens":0.3365,"t9_qualitative_signal_coverage":0.548,"t5_conviction_high_hit_rate_13w":0.0,"t5_conviction_medium_hit_rate_13w":0.0,"t5_conviction_low_hit_rate_13w":0.0,"ib_source_share":0.97,"ib_field_coverage_avg":9.7629,"equity_curve_points_30d":0,"weekly_issues_report_present":true,"open_p0_issues":0},{"timestamp":"2026-06-13T18:00:02.779041+00:00","T5":582.0,"T8":0.0,"T9":0.0,"t9_branch_count_offmain":0.0,"t5_bearish_sell_today":0.0,"t5_audit_dissent_coverage":0.0,"t5_category_score_coverage":0.1598,"t5_expert_panel_coverage_7d":0.0,"T6":0.97,"t6_valuation_coverage":0.9894,"T7":0.03,"t8_universe_coverage":96.0,"t8_local_bars_coverage":1.0,"T4":0.0,"t4_avg_holding_days_closed":34.5833,"T10":1.0,"T2":0.0,"t7_t7_earnings_calendar_freshness":0.0417,"VAL":0.0,"t9_backtest_runs_last_28d":4.0,"t9_weekly_reports_with_scorecard":1.0,"t5_t5_weekly_scorecard_present":0.0,"t9_podcast_transcript_validity":0.9176,"t6_annual_report_corpus_tokens":0.3365,"t9_qualitative_signal_coverage":0.548,"t5_conviction_high_hit_rate_13w":0.0,"t5_conviction_medium_hit_rate_13w":0.0,"t5_conviction_low_hit_rate_13w":0.0,"ib_source_share":0.97,"ib_field_coverage_avg":9.7629,"equity_curve_points_30d":0,"weekly_issues_report_present":true,"open_p0_issues":0},{"timestamp":"2026-06-13T23:00:02.610132+00:00","T5":582.0,"T8":0.0,"T9":0.0,"t9_branch_count_offmain":0.0,"t5_bearish_sell_today":0.0,"t5_audit_dissent_coverage":0.0,"t5_category_score_coverage":0.1598,"t5_expert_panel_coverage_7d":0.0,"T6":0.97,"t6_valuation_coverage":0.9894,"T7":0.0,"t8_universe_coverage":96.0,"t8_local_bars_coverage":1.0,"T4":0.0,"t4_avg_holding_days_closed":34.5833,"T10":1.0,"T2":0.0,"t7_t7_earnings_calendar_freshness":0.0417,"VAL":0.0,"t9_backtest_runs_last_28d":4.0,"t9_weekly_reports_with_scorecard":1.0,"t5_t5_weekly_scorecard_present":0.0,"t9_podcast_transcript_validity":0.9176,"t6_annual_report_corpus_tokens":0.3365,"t9_qualitative_signal_coverage":0.548,"t5_conviction_high_hit_rate_13w":0.0,"t5_conviction_medium_hit_rate_13w":0.0,"t5_conviction_low_hit_rate_13w":0.0,"ib_source_share":0.97,"ib_field_coverage_avg":9.7629,"equity_curve_points_30d":0,"weekly_issues_report_present":true,"open_p0_issues":0},{"timestamp":"2026-06-14T00:30:02.604794+00:00","T5":582.0,"T8":0.0,"T9":0.0,"t9_branch_count_offmain":0.0,"t5_bearish_sell_today":0.0,"t5_audit_dissent_coverage":0.0,"t5_category_score_coverage":0.1598,"t5_expert_panel_coverage_7d":0.0,"T6":0.97,"t6_valuation_coverage":0.9894,"T7":0.0,"t8_universe_coverage":96.0,"t8_local_bars_coverage":1.0,"T4":0.0,"t4_avg_holding_days_closed":34.5833,"T10":1.0,"T2":0.0,"t7_t7_earnings_calendar_freshness":0.0417,"VAL":0.0,"t9_backtest_runs_last_28d":4.0,"t9_weekly_reports_with_scorecard":1.0,"t5_t5_weekly_scorecard_present":0.0,"t9_podcast_transcript_validity":0.9176,"t6_annual_report_corpus_tokens":0.3365,"t9_qualitative_signal_coverage":0.548,"t5_conviction_high_hit_rate_13w":0.0,"t5_conviction_medium_hit_rate_13w":0.0,"t5_conviction_low_hit_rate_13w":0.0,"ib_source_share":0.97,"ib_field_coverage_avg":9.7629,"equity_curve_points_30d":0,"weekly_issues_report_present":true,"open_p0_issues":0},{"timestamp":"2026-06-14T04:30:01.258759+00:00","T5":582.0,"T8":0.0,"T9":0.0,"t9_branch_count_offmain":0.0,"t5_bearish_sell_today":0.0,"t5_audit_dissent_coverage":0.0,"t5_category_score_coverage":0.1598,"t5_expert_panel_coverage_7d":0.0,"T6":0.97,"t6_valuation_coverage":0.9894,"T7":0.0,"t8_universe_coverage":96.0,"t8_local_bars_coverage":1.0,"T4":0.0,"t4_avg_holding_days_closed":34.5833,"T10":1.0,"T2":0.0,"t7_t7_earnings_calendar_freshness":0.0417,"VAL":0.0,"t9_backtest_runs_last_28d":4.0,"t9_weekly_reports_with_scorecard":1.0,"t5_t5_weekly_scorecard_present":0.0,"t9_podcast_transcript_validity":0.9176,"t6_annual_report_corpus_tokens":0.3365,"t9_qualitative_signal_coverage":0.548,"t5_conviction_high_hit_rate_13w":0.0,"t5_conviction_medium_hit_rate_13w":0.0,"t5_conviction_low_hit_rate_13w":0.0,"ib_source_share":0.97,"ib_field_coverage_avg":9.7629,"equity_curve_points_30d":0,"weekly_issues_report_present":true,"open_p0_issues":0},{"timestamp":"2026-06-14T07:30:00.853595+00:00","T5":585.0,"T8":96.0,"T9":0.9062,"t9_branch_count_offmain":0.0,"t5_bearish_sell_today":24.0,"t5_audit_dissent_coverage":0.0158,"t5_category_score_coverage":0.3077,"t5_expert_panel_coverage_7d":0.0,"T6":0.97,"t6_valuation_coverage":0.9893,"T7":0.95,"t8_universe_coverage":96.0,"t8_local_bars_coverage":1.0,"T4":0.0,"t4_avg_holding_days_closed":34.5833,"T10":1.0,"T2":0.0,"t7_t7_earnings_calendar_freshness":0.9062,"VAL":0.0,"t9_backtest_runs_last_28d":4.0,"t9_weekly_reports_with_scorecard":1.0,"t5_t5_weekly_scorecard_present":0.0,"t9_podcast_transcript_validity":0.9176,"t6_annual_report_corpus_tokens":0.3365,"t9_qualitative_signal_coverage":0.5432,"t5_conviction_high_hit_rate_13w":0.0,"t5_conviction_medium_hit_rate_13w":0.0,"t5_conviction_low_hit_rate_13w":0.0,"ib_source_share":0.97,"ib_field_coverage_avg":9.7629,"equity_curve_points_30d":0,"weekly_issues_report_present":true,"open_p0_issues":0},{"timestamp":"2026-06-14T09:00:02.973863+00:00","T5":585.0,"T8":96.0,"T9":0.9062,"t9_branch_count_offmain":0.0,"t5_bearish_sell_today":24.0,"t5_audit_dissent_coverage":0.0158,"t5_category_score_coverage":0.3077,"t5_expert_panel_coverage_7d":0.0,"T6":0.97,"t6_valuation_coverage":0.9893,"T7":0.95,"t8_universe_coverage":96.0,"t8_local_bars_coverage":1.0,"T4":0.0,"t4_avg_holding_days_closed":34.5833,"T10":1.0,"T2":0.0,"t7_t7_earnings_calendar_freshness":0.9062,"VAL":0.0,"t9_backtest_runs_last_28d":4.0,"t9_weekly_reports_with_scorecard":1.0,"t5_t5_weekly_scorecard_present":0.0,"t9_podcast_transcript_validity":0.9176,"t6_annual_report_corpus_tokens":0.3365,"t9_qualitative_signal_coverage":0.5432,"t5_conviction_high_hit_rate_13w":0.0,"t5_conviction_medium_hit_rate_13w":0.0,"t5_conviction_low_hit_rate_13w":0.0,"ib_source_share":0.97,"ib_field_coverage_avg":9.7629,"equity_curve_points_30d":0,"weekly_issues_report_present":true,"open_p0_issues":0},{"timestamp":"2026-06-14T12:00:02.667603+00:00","T5":585.0,"T8":96.0,"T9":0.9062,"t9_branch_count_offmain":0.0,"t5_bearish_sell_today":24.0,"t5_audit_dissent_coverage":0.0158,"t5_category_score_coverage":0.3077,"t5_expert_panel_coverage_7d":0.0,"T6":0.97,"t6_valuation_coverage":0.9893,"T7":0.95,"t8_universe_coverage":96.0,"t8_local_bars_coverage":1.0,"T4":0.0,"t4_avg_holding_days_closed":34.5833,"T10":1.0,"T2":0.0,"t7_t7_earnings_calendar_freshness":0.9062,"VAL":0.0,"t9_backtest_runs_last_28d":4.0,"t9_weekly_reports_with_scorecard":1.0,"t5_t5_weekly_scorecard_present":0.0,"t9_podcast_transcript_validity":0.9176,"t6_annual_report_corpus_tokens":0.3365,"t9_qualitative_signal_coverage":0.5432,"t5_conviction_high_hit_rate_13w":0.0,"t5_conviction_medium_hit_rate_13w":0.0,"t5_conviction_low_hit_rate_13w":0.0,"ib_source_share":0.97,"ib_field_coverage_avg":9.7629,"equity_curve_points_30d":0,"weekly_issues_report_present":true,"open_p0_issues":0},{"timestamp":"2026-06-14T13:30:02.585804+00:00","T5":585.0,"T8":96.0,"T9":0.9062,"t9_branch_count_offmain":0.0,"t5_bearish_sell_today":24.0,"t5_audit_dissent_coverage":0.0158,"t5_category_score_coverage":0.3077,"t5_expert_panel_coverage_7d":0.0,"T6":0.97,"t6_valuation_coverage":0.9893,"T7":0.95,"t8_universe_coverage":96.0,"t8_local_bars_coverage":1.0,"T4":0.0,"t4_avg_holding_days_closed":34.5833,"T10":1.0,"T2":0.0,"t7_t7_earnings_calendar_freshness":0.9062,"VAL":0.0,"t9_backtest_runs_last_28d":4.0,"t9_weekly_reports_with_scorecard":1.0,"t5_t5_weekly_scorecard_present":0.0,"t9_podcast_transcript_validity":0.9176,"t6_annual_report_corpus_tokens":0.3365,"t9_qualitative_signal_coverage":0.5432,"t5_conviction_high_hit_rate_13w":0.0,"t5_conviction_medium_hit_rate_13w":0.0,"t5_conviction_low_hit_rate_13w":0.0,"ib_source_share":0.97,"ib_field_coverage_avg":9.7629,"equity_curve_points_30d":0,"weekly_issues_report_present":true,"open_p0_issues":0},{"timestamp":"2026-06-14T14:30:02.621684+00:00","T5":585.0,"T8":96.0,"T9":0.9062,"t9_branch_count_offmain":0.0,"t5_bearish_sell_today":24.0,"t5_audit_dissent_coverage":0.0158,"t5_category_score_coverage":0.3077,"t5_expert_panel_coverage_7d":0.0,"T6":0.97,"t6_valuation_coverage":0.9893,"T7":0.95,"t8_universe_coverage":96.0,"t8_local_bars_coverage":1.0,"T4":0.0,"t4_avg_holding_days_closed":34.5833,"T10":1.0,"T2":0.0,"t7_t7_earnings_calendar_freshness":0.9062,"VAL":0.0,"t9_backtest_runs_last_28d":4.0,"t9_weekly_reports_with_scorecard":1.0,"t5_t5_weekly_scorecard_present":0.0,"t9_podcast_transcript_validity":0.9176,"t6_annual_report_corpus_tokens":0.3365,"t9_qualitative_signal_coverage":0.5432,"t5_conviction_high_hit_rate_13w":0.0,"t5_conviction_medium_hit_rate_13w":0.0,"t5_conviction_low_hit_rate_13w":0.0,"ib_source_share":0.97,"ib_field_coverage_avg":9.7629,"equity_curve_points_30d":0,"weekly_issues_report_present":true,"open_p0_issues":0},{"timestamp":"2026-06-14T18:00:03.374199+00:00","T5":585.0,"T8":96.0,"T9":0.9062,"t9_branch_count_offmain":0.0,"t5_bearish_sell_today":24.0,"t5_audit_dissent_coverage":0.0158,"t5_category_score_coverage":0.3077,"t5_expert_panel_coverage_7d":0.0,"T6":0.97,"t6_valuation_coverage":0.9893,"T7":0.95,"t8_universe_coverage":96.0,"t8_local_bars_coverage":1.0,"T4":0.0,"t4_avg_holding_days_closed":34.5833,"T10":1.0,"T2":0.0,"t7_t7_earnings_calendar_freshness":0.9062,"VAL":0.0,"t9_backtest_runs_last_28d":4.0,"t9_weekly_reports_with_scorecard":1.0,"t5_t5_weekly_scorecard_present":0.0,"t9_podcast_transcript_validity":0.9176,"t6_annual_report_corpus_tokens":0.3365,"t9_qualitative_signal_coverage":0.5432,"t5_conviction_high_hit_rate_13w":0.0,"t5_conviction_medium_hit_rate_13w":0.0,"t5_conviction_low_hit_rate_13w":0.0,"ib_source_share":0.97,"ib_field_coverage_avg":9.7629,"equity_curve_points_30d":0,"weekly_issues_report_present":true,"open_p0_issues":0},{"timestamp":"2026-06-14T23:00:03.048286+00:00","T5":585.0,"T8":96.0,"T9":0.9062,"t9_branch_count_offmain":0.0,"t5_bearish_sell_today":24.0,"t5_audit_dissent_coverage":0.0158,"t5_category_score_coverage":0.3077,"t5_expert_panel_coverage_7d":0.0,"T6":0.97,"t6_valuation_coverage":0.9893,"T7":0.95,"t8_universe_coverage":96.0,"t8_local_bars_coverage":1.0,"T4":0.0,"t4_avg_holding_days_closed":34.5833,"T10":1.0,"T2":0.0,"t7_t7_earnings_calendar_freshness":0.9062,"VAL":0.0,"t9_backtest_runs_last_28d":4.0,"t9_weekly_reports_with_scorecard":1.0,"t5_t5_weekly_scorecard_present":0.0,"t9_podcast_transcript_validity":0.9176,"t6_annual_report_corpus_tokens":0.3365,"t9_qualitative_signal_coverage":0.5432,"t5_conviction_high_hit_rate_13w":0.0,"t5_conviction_medium_hit_rate_13w":0.0,"t5_conviction_low_hit_rate_13w":0.0,"ib_source_share":0.97,"ib_field_coverage_avg":9.7629,"equity_curve_points_30d":0,"weekly_issues_report_present":true,"open_p0_issues":0},{"timestamp":"2026-06-15T00:30:01.088466+00:00","T5":585.0,"T8":0.0,"T9":0.0,"t9_branch_count_offmain":0.0,"t5_bearish_sell_today":0.0,"t5_audit_dissent_coverage":0.0158,"t5_category_score_coverage":0.3077,"t5_expert_panel_coverage_7d":0.0,"T6":0.97,"t6_valuation_coverage":0.9893,"T7":0.95,"t8_universe_coverage":96.0,"t8_local_bars_coverage":1.0,"T4":0.0,"t4_avg_holding_days_closed":34.5833,"T10":1.0,"T2":0.0,"t7_t7_earnings_calendar_freshness":0.9062,"VAL":0.0,"t9_backtest_runs_last_28d":4.0,"t9_weekly_reports_with_scorecard":1.0,"t5_t5_weekly_scorecard_present":0.0,"t9_podcast_transcript_validity":0.918,"t6_annual_report_corpus_tokens":0.3365,"t9_qualitative_signal_coverage":0.5432,"t5_conviction_high_hit_rate_13w":0.0,"t5_conviction_medium_hit_rate_13w":0.0,"t5_conviction_low_hit_rate_13w":0.0,"ib_source_share":0.97,"ib_field_coverage_avg":9.7629,"equity_curve_points_30d":0,"weekly_issues_report_present":false,"open_p0_issues":0},{"timestamp":"2026-06-15T04:30:00.847447+00:00","T5":585.0,"T8":0.0,"T9":0.0,"t9_branch_count_offmain":0.0,"t5_bearish_sell_today":0.0,"t5_audit_dissent_coverage":0.0158,"t5_category_score_coverage":0.3077,"t5_expert_panel_coverage_7d":0.0,"T6":0.97,"t6_valuation_coverage":0.9893,"T7":0.95,"t8_universe_coverage":96.0,"t8_local_bars_coverage":1.0,"T4":0.0,"t4_avg_holding_days_closed":34.5833,"T10":1.0,"T2":0.0,"t7_t7_earnings_calendar_freshness":0.9062,"VAL":0.0,"t9_backtest_runs_last_28d":4.0,"t9_weekly_reports_with_scorecard":1.0,"t5_t5_weekly_scorecard_present":0.0,"t9_podcast_transcript_validity":0.918,"t6_annual_report_corpus_tokens":0.3365,"t9_qualitative_signal_coverage":0.5432,"t5_conviction_high_hit_rate_13w":0.0,"t5_conviction_medium_hit_rate_13w":0.0,"t5_conviction_low_hit_rate_13w":0.0,"ib_source_share":0.97,"ib_field_coverage_avg":9.7629,"equity_curve_points_30d":0,"weekly_issues_report_present":false,"open_p0_issues":0},{"timestamp":"2026-06-15T07:30:00.850781+00:00","T5":588.0,"T8":96.0,"T9":0.9062,"t9_branch_count_offmain":0.0,"t5_bearish_sell_today":25.0,"t5_audit_dissent_coverage":0.0304,"t5_category_score_coverage":0.449,"t5_expert_panel_coverage_7d":0.0,"T6":0.97,"t6_valuation_coverage":0.9838,"T7":0.02,"t8_universe_coverage":96.0,"t8_local_bars_coverage":1.0,"T4":0.0,"t4_avg_holding_days_closed":37.0,"T10":1.0,"T2":0.0,"t7_t7_earnings_calendar_freshness":0.9062,"VAL":0.0,"t9_backtest_runs_last_28d":4.0,"t9_weekly_reports_with_scorecard":1.0,"t5_t5_weekly_scorecard_present":0.0,"t9_podcast_transcript_validity":0.918,"t6_annual_report_corpus_tokens":0.3365,"t9_qualitative_signal_coverage":0.5348,"t5_conviction_high_hit_rate_13w":0.0,"t5_conviction_medium_hit_rate_13w":0.0,"t5_conviction_low_hit_rate_13w":0.0,"ib_source_share":0.97,"ib_field_coverage_avg":9.7629,"equity_curve_points_30d":0,"weekly_issues_report_present":false,"open_p0_issues":0},{"timestamp":"2026-06-15T09:00:03.304738+00:00","T5":588.0,"T8":96.0,"T9":0.9062,"t9_branch_count_offmain":0.0,"t5_bearish_sell_today":25.0,"t5_audit_dissent_coverage":0.0304,"t5_category_score_coverage":0.449,"t5_expert_panel_coverage_7d":0.0,"T6":0.97,"t6_valuation_coverage":0.9838,"T7":0.02,"t8_universe_coverage":96.0,"t8_local_bars_coverage":1.0,"T4":0.0,"t4_avg_holding_days_closed":37.0,"T10":1.0,"T2":0.0,"t7_t7_earnings_calendar_freshness":0.9062,"VAL":0.0,"t9_backtest_runs_last_28d":4.0,"t9_weekly_reports_with_scorecard":1.0,"t5_t5_weekly_scorecard_present":0.0,"t9_podcast_transcript_validity":0.918,"t6_annual_report_corpus_tokens":0.3365,"t9_qualitative_signal_coverage":0.5348,"t5_conviction_high_hit_rate_13w":0.0,"t5_conviction_medium_hit_rate_13w":0.0,"t5_conviction_low_hit_rate_13w":0.0,"ib_source_share":0.97,"ib_field_coverage_avg":9.7629,"equity_curve_points_30d":0,"weekly_issues_report_present":false,"open_p0_issues":0},{"timestamp":"2026-06-15T12:00:01.110447+00:00","T5":595.0,"T8":96.0,"T9":0.9062,"t9_branch_count_offmain":0.0,"t5_bearish_sell_today":25.0,"t5_audit_dissent_coverage":0.0334,"t5_category_score_coverage":0.4538,"t5_expert_panel_coverage_7d":0.0,"T6":0.97,"t6_valuation_coverage":0.9822,"T7":0.02,"t8_universe_coverage":96.0,"t8_local_bars_coverage":1.0,"T4":0.0,"t4_avg_holding_days_closed":37.0,"T10":1.0,"T2":0.0,"t7_t7_earnings_calendar_freshness":0.9062,"VAL":0.0,"t9_backtest_runs_last_28d":5.0,"t9_weekly_reports_with_scorecard":1.0,"t5_t5_weekly_scorecard_present":0.0,"t9_podcast_transcript_validity":0.918,"t6_annual_report_corpus_tokens":0.3365,"t9_qualitative_signal_coverage":0.5282,"t5_conviction_high_hit_rate_13w":0.0,"t5_conviction_medium_hit_rate_13w":0.0,"t5_conviction_low_hit_rate_13w":0.0,"ib_source_share":0.97,"ib_field_coverage_avg":9.7629,"equity_curve_points_30d":0,"weekly_issues_report_present":true,"open_p0_issues":0},{"timestamp":"2026-06-15T13:30:03.299202+00:00","T5":595.0,"T8":96.0,"T9":0.9062,"t9_branch_count_offmain":0.0,"t5_bearish_sell_today":25.0,"t5_audit_dissent_coverage":0.0334,"t5_category_score_coverage":0.4538,"t5_expert_panel_coverage_7d":0.0,"T6":0.97,"t6_valuation_coverage":0.9822,"T7":0.02,"t8_universe_coverage":96.0,"t8_local_bars_coverage":1.0,"T4":0.0,"t4_avg_holding_days_closed":37.0,"T10":1.0,"T2":0.0,"t7_t7_earnings_calendar_freshness":0.9062,"VAL":0.0,"t9_backtest_runs_last_28d":4.0,"t9_weekly_reports_with_scorecard":1.0,"t5_t5_weekly_scorecard_present":0.0,"t9_podcast_transcript_validity":0.918,"t6_annual_report_corpus_tokens":0.3365,"t9_qualitative_signal_coverage":0.5282,"t5_conviction_high_hit_rate_13w":0.0,"t5_conviction_medium_hit_rate_13w":0.0,"t5_conviction_low_hit_rate_13w":0.0,"ib_source_share":0.97,"ib_field_coverage_avg":9.7629,"equity_curve_points_30d":0,"weekly_issues_report_present":true,"open_p0_issues":0},{"timestamp":"2026-06-15T14:30:03.799790+00:00","T5":595.0,"T8":96.0,"T9":0.9062,"t9_branch_count_offmain":0.0,"t5_bearish_sell_today":25.0,"t5_audit_dissent_coverage":0.0334,"t5_category_score_coverage":0.4538,"t5_expert_panel_coverage_7d":0.0,"T6":0.97,"t6_valuation_coverage":0.9822,"T7":0.02,"t8_universe_coverage":96.0,"t8_local_bars_coverage":1.0,"T4":0.0,"t4_avg_holding_days_closed":37.0,"T10":1.0,"T2":0.0,"t7_t7_earnings_calendar_freshness":0.9062,"VAL":0.0,"t9_backtest_runs_last_28d":4.0,"t9_weekly_reports_with_scorecard":1.0,"t5_t5_weekly_scorecard_present":0.0,"t9_podcast_transcript_validity":0.918,"t6_annual_report_corpus_tokens":0.3365,"t9_qualitative_signal_coverage":0.5282,"t5_conviction_high_hit_rate_13w":0.0,"t5_conviction_medium_hit_rate_13w":0.0,"t5_conviction_low_hit_rate_13w":0.0,"ib_source_share":0.97,"ib_field_coverage_avg":9.7629,"equity_curve_points_30d":0,"weekly_issues_report_present":true,"open_p0_issues":0},{"timestamp":"2026-06-15T18:00:03.067389+00:00","T5":595.0,"T8":96.0,"T9":0.9062,"t9_branch_count_offmain":0.0,"t5_bearish_sell_today":25.0,"t5_audit_dissent_coverage":0.0334,"t5_category_score_coverage":0.4538,"t5_expert_panel_coverage_7d":0.0,"T6":0.97,"t6_valuation_coverage":0.9822,"T7":0.02,"t8_universe_coverage":96.0,"t8_local_bars_coverage":1.0,"T4":0.0,"t4_avg_holding_days_closed":37.0,"T10":1.0,"T2":0.0,"t7_t7_earnings_calendar_freshness":0.9062,"VAL":0.0,"t9_backtest_runs_last_28d":4.0,"t9_weekly_reports_with_scorecard":1.0,"t5_t5_weekly_scorecard_present":0.0,"t9_podcast_transcript_validity":0.918,"t6_annual_report_corpus_tokens":0.3365,"t9_qualitative_signal_coverage":0.5282,"t5_conviction_high_hit_rate_13w":0.0,"t5_conviction_medium_hit_rate_13w":0.0,"t5_conviction_low_hit_rate_13w":0.0,"ib_source_share":0.97,"ib_field_coverage_avg":9.7629,"equity_curve_points_30d":0,"weekly_issues_report_present":true,"open_p0_issues":0},{"timestamp":"2026-06-15T23:00:02.672783+00:00","T5":595.0,"T8":96.0,"T9":0.9062,"t9_branch_count_offmain":0.0,"t5_bearish_sell_today":25.0,"t5_audit_dissent_coverage":0.0334,"t5_category_score_coverage":0.4538,"t5_expert_panel_coverage_7d":0.0,"T6":0.97,"t6_valuation_coverage":0.9822,"T7":0.02,"t8_universe_coverage":96.0,"t8_local_bars_coverage":0.0,"T4":0.0,"t4_avg_holding_days_closed":37.0,"T10":1.0,"T2":0.0,"t7_t7_earnings_calendar_freshness":0.9062,"VAL":0.0,"t9_backtest_runs_last_28d":4.0,"t9_weekly_reports_with_scorecard":1.0,"t5_t5_weekly_scorecard_present":0.0,"t9_podcast_transcript_validity":0.918,"t6_annual_report_corpus_tokens":0.3365,"t9_qualitative_signal_coverage":0.5282,"t5_conviction_high_hit_rate_13w":0.0,"t5_conviction_medium_hit_rate_13w":0.0,"t5_conviction_low_hit_rate_13w":0.0,"ib_source_share":0.97,"ib_field_coverage_avg":9.7629,"equity_curve_points_30d":0,"weekly_issues_report_present":true,"open_p0_issues":0},{"timestamp":"2026-06-16T00:30:01.414991+00:00","T5":595.0,"T8":0.0,"T9":0.0,"t9_branch_count_offmain":0.0,"t5_bearish_sell_today":0.0,"t5_audit_dissent_coverage":0.0334,"t5_category_score_coverage":0.4538,"t5_expert_panel_coverage_7d":0.0,"T6":0.97,"t6_valuation_coverage":0.9822,"T7":0.02,"t8_universe_coverage":96.0,"t8_local_bars_coverage":0.0,"T4":0.0,"t4_avg_holding_days_closed":37.0,"T10":1.0,"T2":0.0,"t7_t7_earnings_calendar_freshness":0.9062,"VAL":0.0,"t9_backtest_runs_last_28d":4.0,"t9_weekly_reports_with_scorecard":1.0,"t5_t5_weekly_scorecard_present":0.0,"t9_podcast_transcript_validity":0.9198,"t6_annual_report_corpus_tokens":0.3365,"t9_qualitative_signal_coverage":0.5282,"t5_conviction_high_hit_rate_13w":0.0,"t5_conviction_medium_hit_rate_13w":0.0,"t5_conviction_low_hit_rate_13w":0.0,"ib_source_share":0.97,"ib_field_coverage_avg":9.7629,"equity_curve_points_30d":0,"weekly_issues_report_present":true,"open_p0_issues":0},{"timestamp":"2026-06-16T04:30:02.232974+00:00","T5":595.0,"T8":0.0,"T9":0.0,"t9_branch_count_offmain":0.0,"t5_bearish_sell_today":0.0,"t5_audit_dissent_coverage":0.0334,"t5_category_score_coverage":0.4538,"t5_expert_panel_coverage_7d":0.0,"T6":0.97,"t6_valuation_coverage":0.9822,"T7":0.02,"t8_universe_coverage":96.0,"t8_local_bars_coverage":0.0,"T4":0.0,"t4_avg_holding_days_closed":37.0,"T10":1.0,"T2":0.0,"t7_t7_earnings_calendar_freshness":0.9062,"VAL":0.0,"t9_backtest_runs_last_28d":4.0,"t9_weekly_reports_with_scorecard":1.0,"t5_t5_weekly_scorecard_present":0.0,"t9_podcast_transcript_validity":0.9198,"t6_annual_report_corpus_tokens":0.3365,"t9_qualitative_signal_coverage":0.5282,"t5_conviction_high_hit_rate_13w":0.0,"t5_conviction_medium_hit_rate_13w":0.0,"t5_conviction_low_hit_rate_13w":0.0,"ib_source_share":0.97,"ib_field_coverage_avg":9.7629,"equity_curve_points_30d":0,"weekly_issues_report_present":true,"open_p0_issues":0},{"timestamp":"2026-06-16T07:30:00.879850+00:00","T5":598.0,"T8":96.0,"T9":0.9062,"t9_branch_count_offmain":0.0,"t5_bearish_sell_today":26.0,"t5_audit_dissent_coverage":0.0498,"t5_category_score_coverage":0.597,"t5_expert_panel_coverage_7d":0.0,"T6":0.06,"t6_valuation_coverage":0.9821,"T7":0.93,"t8_universe_coverage":96.0,"t8_local_bars_coverage":0.5,"T4":0.0,"t4_avg_holding_days_closed":37.0,"T10":1.0,"T2":0.0,"t7_t7_earnings_calendar_freshness":0.9062,"VAL":0.0,"t9_backtest_runs_last_28d":4.0,"t9_weekly_reports_with_scorecard":1.0,"t5_t5_weekly_scorecard_present":0.0,"t9_podcast_transcript_validity":0.9202,"t6_annual_report_corpus_tokens":0.3365,"t9_qualitative_signal_coverage":0.5214,"t5_conviction_high_hit_rate_13w":0.0,"t5_conviction_medium_hit_rate_13w":0.0,"t5_conviction_low_hit_rate_13w":0.0,"ib_source_share":0.06,"ib_field_coverage_avg":10.5,"equity_curve_points_30d":0,"weekly_issues_report_present":true,"open_p0_issues":0},{"timestamp":"2026-06-16T09:00:00.974971+00:00","T5":598.0,"T8":96.0,"T9":0.9062,"t9_branch_count_offmain":0.0,"t5_bearish_sell_today":26.0,"t5_audit_dissent_coverage":0.0498,"t5_category_score_coverage":0.597,"t5_expert_panel_coverage_7d":0.0,"T6":0.06,"t6_valuation_coverage":0.9821,"T7":0.93,"t8_universe_coverage":96.0,"t8_local_bars_coverage":0.5,"T4":0.0,"t4_avg_holding_days_closed":37.0,"T10":1.0,"T2":0.0,"t7_t7_earnings_calendar_freshness":0.9062,"VAL":0.0,"t9_backtest_runs_last_28d":4.0,"t9_weekly_reports_with_scorecard":1.0,"t5_t5_weekly_scorecard_present":0.0,"t9_podcast_transcript_validity":0.9202,"t6_annual_report_corpus_tokens":0.3365,"t9_qualitative_signal_coverage":0.5214,"t5_conviction_high_hit_rate_13w":0.0,"t5_conviction_medium_hit_rate_13w":0.0,"t5_conviction_low_hit_rate_13w":0.0,"ib_source_share":0.06,"ib_field_coverage_avg":10.5,"equity_curve_points_30d":0,"weekly_issues_report_present":true,"open_p0_issues":0},{"timestamp":"2026-06-16T12:00:02.705537+00:00","T5":598.0,"T8":96.0,"T9":0.9062,"t9_branch_count_offmain":0.0,"t5_bearish_sell_today":26.0,"t5_audit_dissent_coverage":0.0498,"t5_category_score_coverage":0.597,"t5_expert_panel_coverage_7d":0.0,"T6":0.06,"t6_valuation_coverage":0.9821,"T7":0.93,"t8_universe_coverage":96.0,"t8_local_bars_coverage":0.5,"T4":0.0,"t4_avg_holding_days_closed":37.0,"T10":1.0,"T2":0.0,"t7_t7_earnings_calendar_freshness":0.9062,"VAL":0.0,"t9_backtest_runs_last_28d":4.0,"t9_weekly_reports_with_scorecard":1.0,"t5_t5_weekly_scorecard_present":0.0,"t9_podcast_transcript_validity":0.9202,"t6_annual_report_corpus_tokens":0.3365,"t9_qualitative_signal_coverage":0.5214,"t5_conviction_high_hit_rate_13w":0.0,"t5_conviction_medium_hit_rate_13w":0.0,"t5_conviction_low_hit_rate_13w":0.0,"ib_source_share":0.06,"ib_field_coverage_avg":10.5,"equity_curve_points_30d":0,"weekly_issues_report_present":true,"open_p0_issues":0},{"timestamp":"2026-06-16T13:30:03.227230+00:00","T5":598.0,"T8":96.0,"T9":0.9062,"t9_branch_count_offmain":0.0,"t5_bearish_sell_today":26.0,"t5_audit_dissent_coverage":0.0498,"t5_category_score_coverage":0.597,"t5_expert_panel_coverage_7d":0.0,"T6":0.06,"t6_valuation_coverage":0.9821,"T7":0.93,"t8_universe_coverage":96.0,"t8_local_bars_coverage":0.5,"T4":0.0,"t4_avg_holding_days_closed":37.0,"T10":1.0,"T2":0.0,"t7_t7_earnings_calendar_freshness":0.9062,"VAL":0.0,"t9_backtest_runs_last_28d":4.0,"t9_weekly_reports_with_scorecard":1.0,"t5_t5_weekly_scorecard_present":0.0,"t9_podcast_transcript_validity":0.9202,"t6_annual_report_corpus_tokens":0.3365,"t9_qualitative_signal_coverage":0.5214,"t5_conviction_high_hit_rate_13w":0.0,"t5_conviction_medium_hit_rate_13w":0.0,"t5_conviction_low_hit_rate_13w":0.0,"ib_source_share":0.06,"ib_field_coverage_avg":10.5,"equity_curve_points_30d":0,"weekly_issues_report_present":true,"open_p0_issues":0},{"timestamp":"2026-06-16T14:30:02.776712+00:00","T5":598.0,"T8":96.0,"T9":0.9062,"t9_branch_count_offmain":0.0,"t5_bearish_sell_today":26.0,"t5_audit_dissent_coverage":0.0498,"t5_category_score_coverage":0.597,"t5_expert_panel_coverage_7d":0.0,"T6":0.06,"t6_valuation_coverage":0.9821,"T7":0.93,"t8_universe_coverage":96.0,"t8_local_bars_coverage":0.5,"T4":0.0,"t4_avg_holding_days_closed":37.0,"T10":1.0,"T2":0.0,"t7_t7_earnings_calendar_freshness":0.9062,"VAL":0.0,"t9_backtest_runs_last_28d":4.0,"t9_weekly_reports_with_scorecard":1.0,"t5_t5_weekly_scorecard_present":0.0,"t9_podcast_transcript_validity":0.9202,"t6_annual_report_corpus_tokens":0.3365,"t9_qualitative_signal_coverage":0.5214,"t5_conviction_high_hit_rate_13w":0.0,"t5_conviction_medium_hit_rate_13w":0.0,"t5_conviction_low_hit_rate_13w":0.0,"ib_source_share":0.06,"ib_field_coverage_avg":10.5,"equity_curve_points_30d":0,"weekly_issues_report_present":true,"open_p0_issues":0},{"timestamp":"2026-06-16T18:00:02.916958+00:00","T5":598.0,"T8":96.0,"T9":0.9062,"t9_branch_count_offmain":0.0,"t5_bearish_sell_today":26.0,"t5_audit_dissent_coverage":0.0498,"t5_category_score_coverage":0.597,"t5_expert_panel_coverage_7d":0.0,"T6":0.06,"t6_valuation_coverage":0.9821,"T7":0.93,"t8_universe_coverage":96.0,"t8_local_bars_coverage":0.5,"T4":0.0,"t4_avg_holding_days_closed":37.0,"T10":1.0,"T2":0.0,"t7_t7_earnings_calendar_freshness":0.9062,"VAL":0.0,"t9_backtest_runs_last_28d":4.0,"t9_weekly_reports_with_scorecard":1.0,"t5_t5_weekly_scorecard_present":0.0,"t9_podcast_transcript_validity":0.9202,"t6_annual_report_corpus_tokens":0.3365,"t9_qualitative_signal_coverage":0.5214,"t5_conviction_high_hit_rate_13w":0.0,"t5_conviction_medium_hit_rate_13w":0.0,"t5_conviction_low_hit_rate_13w":0.0,"ib_source_share":0.06,"ib_field_coverage_avg":10.5,"equity_curve_points_30d":0,"weekly_issues_report_present":true,"open_p0_issues":0},{"timestamp":"2026-06-16T23:00:02.869608+00:00","T5":598.0,"T8":96.0,"T9":0.9062,"t9_branch_count_offmain":0.0,"t5_bearish_sell_today":26.0,"t5_audit_dissent_coverage":0.0498,"t5_category_score_coverage":0.597,"t5_expert_panel_coverage_7d":0.0,"T6":0.06,"t6_valuation_coverage":0.9821,"T7":0.93,"t8_universe_coverage":96.0,"t8_local_bars_coverage":0.5,"T4":0.0,"t4_avg_holding_days_closed":37.0,"T10":1.0,"T2":0.0,"t7_t7_earnings_calendar_freshness":0.9062,"VAL":0.0,"t9_backtest_runs_last_28d":4.0,"t9_weekly_reports_with_scorecard":1.0,"t5_t5_weekly_scorecard_present":0.0,"t9_podcast_transcript_validity":0.9202,"t6_annual_report_corpus_tokens":0.3365,"t9_qualitative_signal_coverage":0.5214,"t5_conviction_high_hit_rate_13w":0.0,"t5_conviction_medium_hit_rate_13w":0.0,"t5_conviction_low_hit_rate_13w":0.0,"ib_source_share":0.06,"ib_field_coverage_avg":10.5,"equity_curve_points_30d":0,"weekly_issues_report_present":true,"open_p0_issues":0},{"timestamp":"2026-06-17T00:30:01.401968+00:00","T5":598.0,"T8":0.0,"T9":0.0,"t9_branch_count_offmain":0.0,"t5_bearish_sell_today":0.0,"t5_audit_dissent_coverage":0.0498,"t5_category_score_coverage":0.597,"t5_expert_panel_coverage_7d":0.0,"T6":0.06,"t6_valuation_coverage":0.9821,"T7":0.93,"t8_universe_coverage":96.0,"t8_local_bars_coverage":0.5,"T4":0.0,"t4_avg_holding_days_closed":37.0,"T10":1.0,"T2":0.0,"t7_t7_earnings_calendar_freshness":0.9062,"VAL":0.0,"t9_backtest_runs_last_28d":4.0,"t9_weekly_reports_with_scorecard":1.0,"t5_t5_weekly_scorecard_present":0.0,"t9_podcast_transcript_validity":0.9223,"t6_annual_report_corpus_tokens":0.3365,"t9_qualitative_signal_coverage":0.5214,"t5_conviction_high_hit_rate_13w":0.0,"t5_conviction_medium_hit_rate_13w":0.0,"t5_conviction_low_hit_rate_13w":0.0,"ib_source_share":0.06,"ib_field_coverage_avg":10.5,"equity_curve_points_30d":0,"weekly_issues_report_present":true,"open_p0_issues":0},{"timestamp":"2026-06-17T04:30:01.101322+00:00","T5":598.0,"T8":0.0,"T9":0.0,"t9_branch_count_offmain":0.0,"t5_bearish_sell_today":0.0,"t5_audit_dissent_coverage":0.0498,"t5_category_score_coverage":0.597,"t5_expert_panel_coverage_7d":0.0,"T6":0.06,"t6_valuation_coverage":0.9821,"T7":0.93,"t8_universe_coverage":96.0,"t8_local_bars_coverage":0.5,"T4":0.0,"t4_avg_holding_days_closed":37.0,"T10":1.0,"T2":0.0,"t7_t7_earnings_calendar_freshness":0.9062,"VAL":0.0,"t9_backtest_runs_last_28d":4.0,"t9_weekly_reports_with_scorecard":1.0,"t5_t5_weekly_scorecard_present":0.0,"t9_podcast_transcript_validity":0.9223,"t6_annual_report_corpus_tokens":0.3365,"t9_qualitative_signal_coverage":0.5214,"t5_conviction_high_hit_rate_13w":0.0,"t5_conviction_medium_hit_rate_13w":0.0,"t5_conviction_low_hit_rate_13w":0.0,"ib_source_share":0.06,"ib_field_coverage_avg":10.5,"equity_curve_points_30d":0,"weekly_issues_report_present":true,"open_p0_issues":0},{"timestamp":"2026-06-17T07:30:00.861709+00:00","T5":601.0,"T8":96.0,"T9":0.9062,"t9_branch_count_offmain":0.0,"t5_bearish_sell_today":26.0,"t5_audit_dissent_coverage":0.0655,"t5_category_score_coverage":0.7388,"t5_expert_panel_coverage_7d":0.0,"T6":0.06,"t6_valuation_coverage":0.9819,"T7":0.93,"t8_universe_coverage":96.0,"t8_local_bars_coverage":0.9062,"T4":0.0,"t4_avg_holding_days_closed":37.0,"T10":1.0,"T2":0.0,"t7_t7_earnings_calendar_freshness":0.9062,"VAL":0.0,"t9_backtest_runs_last_28d":4.0,"t9_weekly_reports_with_scorecard":1.0,"t5_t5_weekly_scorecard_present":0.0,"t9_podcast_transcript_validity":0.9223,"t6_annual_report_corpus_tokens":0.3365,"t9_qualitative_signal_coverage":0.5144,"t5_conviction_high_hit_rate_13w":0.0,"t5_conviction_medium_hit_rate_13w":0.0,"t5_conviction_low_hit_rate_13w":0.0,"ib_source_share":0.06,"ib_field_coverage_avg":10.5,"equity_curve_points_30d":0,"weekly_issues_report_present":true,"open_p0_issues":0},{"timestamp":"2026-06-17T09:00:03.020542+00:00","T5":601.0,"T8":96.0,"T9":0.9062,"t9_branch_count_offmain":0.0,"t5_bearish_sell_today":26.0,"t5_audit_dissent_coverage":0.0655,"t5_category_score_coverage":0.7388,"t5_expert_panel_coverage_7d":0.0,"T6":0.06,"t6_valuation_coverage":0.9819,"T7":0.93,"t8_universe_coverage":96.0,"t8_local_bars_coverage":0.9062,"T4":0.0,"t4_avg_holding_days_closed":37.0,"T10":1.0,"T2":0.0,"t7_t7_earnings_calendar_freshness":0.9062,"VAL":0.0,"t9_backtest_runs_last_28d":4.0,"t9_weekly_reports_with_scorecard":1.0,"t5_t5_weekly_scorecard_present":0.0,"t9_podcast_transcript_validity":0.9223,"t6_annual_report_corpus_tokens":0.3365,"t9_qualitative_signal_coverage":0.5144,"t5_conviction_high_hit_rate_13w":0.0,"t5_conviction_medium_hit_rate_13w":0.0,"t5_conviction_low_hit_rate_13w":0.0,"ib_source_share":0.06,"ib_field_coverage_avg":10.5,"equity_curve_points_30d":0,"weekly_issues_report_present":true,"open_p0_issues":0},{"timestamp":"2026-06-17T12:00:01.108606+00:00","T5":610.0,"T8":96.0,"T9":0.9062,"t9_branch_count_offmain":0.0,"t5_bearish_sell_today":28.0,"t5_audit_dissent_coverage":0.069,"t5_category_score_coverage":0.741,"t5_expert_panel_coverage_7d":0.0,"T6":0.06,"t6_valuation_coverage":0.9804,"T7":0.93,"t8_universe_coverage":96.0,"t8_local_bars_coverage":0.9062,"T4":0.0,"t4_avg_holding_days_closed":36.0625,"T10":1.0,"T2":0.0,"t7_t7_earnings_calendar_freshness":0.9062,"VAL":0.0,"t9_backtest_runs_last_28d":4.0,"t9_weekly_reports_with_scorecard":1.0,"t5_t5_weekly_scorecard_present":0.0,"t9_podcast_transcript_validity":0.9223,"t6_annual_report_corpus_tokens":0.3365,"t9_qualitative_signal_coverage":0.5062,"t5_conviction_high_hit_rate_13w":0.0,"t5_conviction_medium_hit_rate_13w":0.0,"t5_conviction_low_hit_rate_13w":0.0,"ib_source_share":0.06,"ib_field_coverage_avg":10.5,"equity_curve_points_30d":0,"weekly_issues_report_present":true,"open_p0_issues":0},{"timestamp":"2026-06-17T13:30:03.796519+00:00","T5":609.0,"T8":96.0,"T9":0.9062,"t9_branch_count_offmain":0.0,"t5_bearish_sell_today":28.0,"t5_audit_dissent_coverage":0.069,"t5_category_score_coverage":0.7422,"t5_expert_panel_coverage_7d":0.0,"T6":0.06,"t6_valuation_coverage":0.9804,"T7":0.93,"t8_universe_coverage":96.0,"t8_local_bars_coverage":0.9062,"T4":0.0,"t4_avg_holding_days_closed":36.0625,"T10":1.0,"T2":0.0,"t7_t7_earnings_calendar_freshness":0.9062,"VAL":0.0,"t9_backtest_runs_last_28d":4.0,"t9_weekly_reports_with_scorecard":1.0,"t5_t5_weekly_scorecard_present":0.0,"t9_podcast_transcript_validity":0.9223,"t6_annual_report_corpus_tokens":0.3365,"t9_qualitative_signal_coverage":0.5071,"t5_conviction_high_hit_rate_13w":0.0,"t5_conviction_medium_hit_rate_13w":0.0,"t5_conviction_low_hit_rate_13w":0.0,"ib_source_share":0.06,"ib_field_coverage_avg":10.5,"equity_curve_points_30d":0,"weekly_issues_report_present":true,"open_p0_issues":0},{"timestamp":"2026-06-17T14:30:02.737703+00:00","T5":609.0,"T8":96.0,"T9":0.9062,"t9_branch_count_offmain":0.0,"t5_bearish_sell_today":28.0,"t5_audit_dissent_coverage":0.069,"t5_category_score_coverage":0.7422,"t5_expert_panel_coverage_7d":0.0,"T6":0.06,"t6_valuation_coverage":0.9804,"T7":0.93,"t8_universe_coverage":96.0,"t8_local_bars_coverage":0.9062,"T4":0.0,"t4_avg_holding_days_closed":36.0625,"T10":1.0,"T2":0.0,"t7_t7_earnings_calendar_freshness":0.9062,"VAL":0.0,"t9_backtest_runs_last_28d":4.0,"t9_weekly_reports_with_scorecard":1.0,"t5_t5_weekly_scorecard_present":0.0,"t9_podcast_transcript_validity":0.9223,"t6_annual_report_corpus_tokens":0.3365,"t9_qualitative_signal_coverage":0.5071,"t5_conviction_high_hit_rate_13w":0.0,"t5_conviction_medium_hit_rate_13w":0.0,"t5_conviction_low_hit_rate_13w":0.0,"ib_source_share":0.06,"ib_field_coverage_avg":10.5,"equity_curve_points_30d":0,"weekly_issues_report_present":true,"open_p0_issues":0},{"timestamp":"2026-06-17T18:00:03.195674+00:00","T5":608.0,"T8":96.0,"T9":0.9062,"t9_branch_count_offmain":0.0,"t5_bearish_sell_today":28.0,"t5_audit_dissent_coverage":0.069,"t5_category_score_coverage":0.7434,"t5_expert_panel_coverage_7d":0.0,"T6":0.06,"t6_valuation_coverage":0.9804,"T7":0.93,"t8_universe_coverage":96.0,"t8_local_bars_coverage":0.9062,"T4":0.0,"t4_avg_holding_days_closed":36.0625,"T10":1.0,"T2":0.0,"t7_t7_earnings_calendar_freshness":0.9062,"VAL":0.0,"t9_backtest_runs_last_28d":4.0,"t9_weekly_reports_with_scorecard":1.0,"t5_t5_weekly_scorecard_present":0.0,"t9_podcast_transcript_validity":0.9223,"t6_annual_report_corpus_tokens":0.3365,"t9_qualitative_signal_coverage":0.508,"t5_conviction_high_hit_rate_13w":0.0,"t5_conviction_medium_hit_rate_13w":0.0,"t5_conviction_low_hit_rate_13w":0.0,"ib_source_share":0.06,"ib_field_coverage_avg":10.5,"equity_curve_points_30d":0,"weekly_issues_report_present":true,"open_p0_issues":0},{"timestamp":"2026-06-17T23:00:02.890783+00:00","T5":608.0,"T8":96.0,"T9":0.9062,"t9_branch_count_offmain":0.0,"t5_bearish_sell_today":28.0,"t5_audit_dissent_coverage":0.069,"t5_category_score_coverage":0.7434,"t5_expert_panel_coverage_7d":0.0,"T6":0.06,"t6_valuation_coverage":0.9804,"T7":0.93,"t8_universe_coverage":96.0,"t8_local_bars_coverage":0.9062,"T4":0.0,"t4_avg_holding_days_closed":36.0625,"T10":1.0,"T2":0.0,"t7_t7_earnings_calendar_freshness":0.9062,"VAL":0.0,"t9_backtest_runs_last_28d":4.0,"t9_weekly_reports_with_scorecard":1.0,"t5_t5_weekly_scorecard_present":0.0,"t9_podcast_transcript_validity":0.9223,"t6_annual_report_corpus_tokens":0.3365,"t9_qualitative_signal_coverage":0.508,"t5_conviction_high_hit_rate_13w":0.0,"t5_conviction_medium_hit_rate_13w":0.0,"t5_conviction_low_hit_rate_13w":0.0,"t8_graph_coverage":1.0,"t8_graph_precision_validated_share":1.0,"t5_t5_supply_chain_signals_7d":0.0,"ib_source_share":0.06,"ib_field_coverage_avg":10.5,"equity_curve_points_30d":0,"weekly_issues_report_present":true,"open_p0_issues":0},{"timestamp":"2026-06-18T04:30:00.868012+00:00","T5":608.0,"T8":0.0,"T9":0.0,"t9_branch_count_offmain":0.0,"t5_bearish_sell_today":0.0,"t5_audit_dissent_coverage":0.069,"t5_category_score_coverage":0.7434,"t5_expert_panel_coverage_7d":0.0,"T6":0.06,"t6_valuation_coverage":0.9804,"T7":0.93,"t8_universe_coverage":96.0,"t8_local_bars_coverage":0.9062,"T4":0.0,"t4_avg_holding_days_closed":36.0625,"T10":1.0,"T2":0.0,"t7_t7_earnings_calendar_freshness":0.9062,"VAL":0.0,"t9_backtest_runs_last_28d":4.0,"t9_weekly_reports_with_scorecard":1.0,"t5_t5_weekly_scorecard_present":0.0,"t9_podcast_transcript_validity":0.9239,"t6_annual_report_corpus_tokens":0.3365,"t9_qualitative_signal_coverage":0.508,"t5_conviction_high_hit_rate_13w":0.0,"t5_conviction_medium_hit_rate_13w":0.0,"t5_conviction_low_hit_rate_13w":0.0,"t8_graph_coverage":1.0,"t8_graph_precision_validated_share":1.0,"t5_t5_supply_chain_signals_7d":0.0,"ib_source_share":0.06,"ib_field_coverage_avg":10.5,"equity_curve_points_30d":0,"weekly_issues_report_present":true,"open_p0_issues":0},{"timestamp":"2026-06-18T07:30:00.901599+00:00","T5":704.0,"T8":96.0,"T9":0.9062,"t9_branch_count_offmain":0.0,"t5_bearish_sell_today":25.0,"t5_audit_dissent_coverage":0.0839,"t5_category_score_coverage":0.7656,"t5_expert_panel_coverage_7d":0.0,"T6":0.06,"t6_valuation_coverage":0.9831,"T7":0.93,"t8_universe_coverage":96.0,"t8_local_bars_coverage":0.9062,"T4":0.0,"t4_avg_holding_days_closed":36.0625,"T10":1.0,"T2":0.0,"t7_t7_earnings_calendar_freshness":0.9062,"VAL":0.0,"t9_backtest_runs_last_28d":4.0,"t9_weekly_reports_with_scorecard":1.0,"t5_t5_weekly_scorecard_present":0.0,"t9_podcast_transcript_validity":0.9239,"t6_annual_report_corpus_tokens":0.3365,"t9_qualitative_signal_coverage":0.5123,"t5_conviction_high_hit_rate_13w":0.0,"t5_conviction_medium_hit_rate_13w":0.0,"t5_conviction_low_hit_rate_13w":0.0,"t8_graph_coverage":1.0,"t8_graph_precision_validated_share":1.0,"t5_t5_supply_chain_signals_7d":0.0,"ib_source_share":0.06,"ib_field_coverage_avg":10.5,"equity_curve_points_30d":0,"weekly_issues_report_present":true,"open_p0_issues":0},{"timestamp":"2026-06-18T11:00:28.831527+00:00","T5":713.0,"T8":96.0,"T9":1.0,"t9_branch_count_offmain":55.0,"t5_bearish_sell_today":27.0,"t5_audit_dissent_coverage":0.0874,"t5_category_score_coverage":0.7672,"t5_expert_panel_coverage_7d":0.0,"T6":0.06,"t6_valuation_coverage":0.9818,"T7":0.93,"t8_universe_coverage":96.0,"t8_local_bars_coverage":0.0,"T4":0.0,"t4_avg_holding_days_closed":36.0625,"T10":1.0,"T2":0.0,"t7_t7_earnings_calendar_freshness":0.9062,"VAL":0.0,"t9_backtest_runs_last_28d":19.0,"t9_weekly_reports_with_scorecard":1.0,"t5_t5_weekly_scorecard_present":0.0,"t9_podcast_transcript_validity":0.9645,"t6_annual_report_corpus_tokens":0.3365,"t9_qualitative_signal_coverage":0.5053,"t5_conviction_high_hit_rate_13w":0.0,"t5_conviction_medium_hit_rate_13w":0.0,"t5_conviction_low_hit_rate_13w":0.0,"t8_graph_coverage":1.0,"t8_graph_precision_validated_share":1.0,"t5_t5_supply_chain_signals_7d":0.0,"ib_source_share":0.06,"ib_field_coverage_avg":10.5,"equity_curve_points_30d":0,"weekly_issues_report_present":true,"open_p0_issues":0},{"timestamp":"2026-06-18T14:00:29.287511+00:00","T5":612.0,"T8":96.0,"T9":1.0,"t9_branch_count_offmain":56.0,"t5_bearish_sell_today":27.0,"t5_audit_dissent_coverage":0.0882,"t5_category_score_coverage":0.8971,"t5_expert_panel_coverage_7d":0.0,"T6":0.06,"t6_valuation_coverage":0.9839,"T7":0.93,"t8_universe_coverage":96.0,"t8_local_bars_coverage":1.0,"T4":0.0,"t4_avg_holding_days_closed":36.0625,"T10":1.0,"T2":0.0,"t7_t7_earnings_calendar_freshness":0.9062,"VAL":0.0,"t9_backtest_runs_last_28d":19.0,"t9_weekly_reports_with_scorecard":1.0,"t5_t5_weekly_scorecard_present":1.0,"t9_podcast_transcript_validity":0.9652,"t6_annual_report_corpus_tokens":0.3365,"t9_qualitative_signal_coverage":0.5054,"t5_conviction_high_hit_rate_13w":0.0,"t5_conviction_medium_hit_rate_13w":0.0,"t5_conviction_low_hit_rate_13w":0.0,"t8_graph_coverage":1.0,"t8_graph_precision_validated_share":1.0,"t5_t5_supply_chain_signals_7d":0.0,"ib_source_share":0.06,"ib_field_coverage_avg":10.5,"equity_curve_points_30d":0,"weekly_issues_report_present":true,"open_p0_issues":0},{"timestamp":"2026-06-18T20:00:28.929505+00:00","T5":612.0,"T8":96.0,"T9":1.0,"t9_branch_count_offmain":56.0,"t5_bearish_sell_today":27.0,"t5_audit_dissent_coverage":0.8333,"t5_category_score_coverage":0.9839,"t5_expert_panel_coverage_7d":0.0,"T6":0.06,"t6_valuation_coverage":0.9839,"T7":0.93,"t8_universe_coverage":96.0,"t8_local_bars_coverage":1.0,"T4":0.0,"t4_avg_holding_days_closed":36.0625,"T10":1.0,"T2":0.0,"t7_t7_earnings_calendar_freshness":0.9062,"VAL":0.0,"t9_backtest_runs_last_28d":19.0,"t9_weekly_reports_with_scorecard":1.0,"t5_t5_weekly_scorecard_present":1.0,"t9_podcast_transcript_validity":0.9652,"t6_annual_report_corpus_tokens":0.3365,"t9_qualitative_signal_coverage":0.5054,"t5_conviction_high_hit_rate_13w":0.0,"t5_conviction_medium_hit_rate_13w":0.0,"t5_conviction_low_hit_rate_13w":0.0,"t8_graph_coverage":1.0,"t8_graph_precision_validated_share":1.0,"t5_t5_supply_chain_signals_7d":0.0,"ib_source_share":0.06,"ib_field_coverage_avg":10.5,"equity_curve_points_30d":0,"weekly_issues_report_present":true,"open_p0_issues":0},{"timestamp":"2026-06-19T05:54:37.862191+00:00","T5":612.0,"T8":0.0,"T9":0.0,"t9_branch_count_offmain":58.0,"t5_bearish_sell_today":0.0,"t5_audit_dissent_coverage":0.8333,"t5_category_score_coverage":0.9839,"t5_expert_panel_coverage_7d":0.0,"T6":0.06,"t6_valuation_coverage":0.9839,"T7":0.93,"t8_universe_coverage":96.0,"t8_local_bars_coverage":1.0,"T4":0.0,"t4_avg_holding_days_closed":36.0625,"T10":1.0,"T2":0.0,"t7_t7_earnings_calendar_freshness":0.8646,"VAL":0.0,"t9_backtest_runs_last_28d":19.0,"t9_weekly_reports_with_scorecard":1.0,"t5_t5_weekly_scorecard_present":1.0,"t9_podcast_transcript_validity":0.9652,"t6_annual_report_corpus_tokens":0.3365,"t9_qualitative_signal_coverage":0.5054,"t5_conviction_high_hit_rate_13w":0.0,"t5_conviction_medium_hit_rate_13w":0.0,"t5_conviction_low_hit_rate_13w":0.0,"t8_graph_coverage":1.0,"t8_graph_precision_validated_share":1.0,"t5_t5_supply_chain_signals_7d":0.0,"ib_source_share":0.06,"ib_field_coverage_avg":10.5,"equity_curve_points_30d":0,"weekly_issues_report_present":true,"open_p0_issues":0},{"timestamp":"2026-06-19T06:30:03.456477+00:00","T5":516.0,"T8":0.0,"T9":0.0,"t9_branch_count_offmain":58.0,"t5_bearish_sell_today":0.0,"t5_audit_dissent_coverage":0.9686,"t5_category_score_coverage":0.9809,"t5_expert_panel_coverage_7d":0.0,"T6":0.06,"t6_valuation_coverage":0.9809,"T7":0.93,"t8_universe_coverage":96.0,"t8_local_bars_coverage":1.0,"T4":0.0,"t4_avg_holding_days_closed":36.0625,"T10":1.0,"T2":0.0,"t7_t7_earnings_calendar_freshness":0.8646,"VAL":0.0,"t9_backtest_runs_last_28d":19.0,"t9_weekly_reports_with_scorecard":1.0,"t5_t5_weekly_scorecard_present":1.0,"t9_podcast_transcript_validity":0.9653,"t6_annual_report_corpus_tokens":0.3365,"t9_qualitative_signal_coverage":0.4968,"t5_conviction_high_hit_rate_13w":0.0,"t5_conviction_medium_hit_rate_13w":0.0,"t5_conviction_low_hit_rate_13w":0.0,"t8_graph_coverage":1.0,"t8_graph_precision_validated_share":1.0,"t5_t5_supply_chain_signals_7d":0.0,"ib_source_share":0.06,"ib_field_coverage_avg":10.5,"equity_curve_points_30d":0,"weekly_issues_report_present":true,"open_p0_issues":0},{"timestamp":"2026-06-19T11:00:03.212236+00:00","T5":612.0,"T8":96.0,"T9":0.9062,"t9_branch_count_offmain":58.0,"t5_bearish_sell_today":23.0,"t5_audit_dissent_coverage":0.973,"t5_category_score_coverage":0.9803,"t5_expert_panel_coverage_7d":0.1308,"T6":0.06,"t6_valuation_coverage":0.9803,"T7":0.93,"t8_universe_coverage":96.0,"t8_local_bars_coverage":1.0,"T4":0.0,"t4_avg_holding_days_closed":38.2778,"T10":1.0,"T2":0.0,"t7_t7_earnings_calendar_freshness":0.9062,"VAL":0.0,"t9_backtest_runs_last_28d":19.0,"t9_weekly_reports_with_scorecard":1.0,"t5_t5_weekly_scorecard_present":1.0,"t9_podcast_transcript_validity":0.9673,"t6_annual_report_corpus_tokens":0.3365,"t9_qualitative_signal_coverage":0.5036,"t5_conviction_high_hit_rate_13w":0.0,"t5_conviction_medium_hit_rate_13w":0.0,"t5_conviction_low_hit_rate_13w":0.0,"t8_graph_coverage":1.0,"t8_graph_precision_validated_share":1.0,"t5_t5_supply_chain_signals_7d":0.0,"ib_source_share":0.06,"ib_field_coverage_avg":10.5,"equity_curve_points_30d":0,"weekly_issues_report_present":true,"open_p0_issues":0},{"timestamp":"2026-06-19T14:00:40.348851+00:00","T5":617.0,"T8":96.0,"T9":0.9062,"t9_branch_count_offmain":58.0,"t5_bearish_sell_today":25.0,"t5_audit_dissent_coverage":1.0,"t5_category_score_coverage":0.9769,"t5_expert_panel_coverage_7d":0.1297,"T6":0.06,"t6_valuation_coverage":0.9769,"T7":0.93,"t8_universe_coverage":96.0,"t8_local_bars_coverage":1.0,"T4":0.0,"t4_avg_holding_days_closed":38.2778,"T10":1.0,"T2":0.0,"t7_t7_earnings_calendar_freshness":0.9062,"VAL":0.0,"t9_backtest_runs_last_28d":19.0,"t9_weekly_reports_with_scorecard":1.0,"t5_t5_weekly_scorecard_present":1.0,"t9_podcast_transcript_validity":0.9674,"t6_annual_report_corpus_tokens":0.3367,"t9_qualitative_signal_coverage":0.4991,"t5_conviction_high_hit_rate_13w":0.0,"t5_conviction_medium_hit_rate_13w":0.0,"t5_conviction_low_hit_rate_13w":0.0,"t8_graph_coverage":1.0,"t8_graph_precision_validated_share":1.0,"t5_t5_supply_chain_signals_7d":0.0,"ib_source_share":0.06,"ib_field_coverage_avg":10.5,"equity_curve_points_30d":0,"weekly_issues_report_present":true,"open_p0_issues":0},{"timestamp":"2026-06-19T16:30:40.226835+00:00","T5":617.0,"T8":96.0,"T9":0.9062,"t9_branch_count_offmain":58.0,"t5_bearish_sell_today":25.0,"t5_audit_dissent_coverage":1.0,"t5_category_score_coverage":0.9769,"t5_expert_panel_coverage_7d":0.1297,"T6":0.06,"t6_valuation_coverage":0.9769,"T7":0.93,"t8_universe_coverage":96.0,"t8_local_bars_coverage":1.0,"T4":0.0,"t4_avg_holding_days_closed":38.2778,"T10":1.0,"T2":0.0,"t7_t7_earnings_calendar_freshness":0.9062,"VAL":0.0,"t9_backtest_runs_last_28d":19.0,"t9_weekly_reports_with_scorecard":1.0,"t5_t5_weekly_scorecard_present":1.0,"t9_podcast_transcript_validity":0.9674,"t6_annual_report_corpus_tokens":0.3367,"t9_qualitative_signal_coverage":0.4991,"t5_conviction_high_hit_rate_13w":0.0,"t5_conviction_medium_hit_rate_13w":0.0,"t5_conviction_low_hit_rate_13w":0.0,"t8_graph_coverage":1.0,"t8_graph_precision_validated_share":1.0,"t5_t5_supply_chain_signals_7d":0.0,"ib_source_share":0.06,"ib_field_coverage_avg":10.5,"equity_curve_points_30d":0,"weekly_issues_report_present":true,"open_p0_issues":0},{"timestamp":"2026-06-19T20:00:40.848799+00:00","T5":617.0,"T8":96.0,"T9":0.9062,"t9_branch_count_offmain":58.0,"t5_bearish_sell_today":25.0,"t5_audit_dissent_coverage":1.0,"t5_category_score_coverage":0.9769,"t5_expert_panel_coverage_7d":0.1297,"T6":0.06,"t6_valuation_coverage":0.9769,"T7":0.93,"t8_universe_coverage":96.0,"t8_local_bars_coverage":1.0,"T4":0.0,"t4_avg_holding_days_closed":38.2778,"T10":1.0,"T2":0.0,"t7_t7_earnings_calendar_freshness":0.9062,"VAL":0.0,"t9_backtest_runs_last_28d":19.0,"t9_weekly_reports_with_scorecard":1.0,"t5_t5_weekly_scorecard_present":1.0,"t9_podcast_transcript_validity":0.9674,"t6_annual_report_corpus_tokens":0.3367,"t9_qualitative_signal_coverage":0.4991,"t5_conviction_high_hit_rate_13w":0.0,"t5_conviction_medium_hit_rate_13w":0.0,"t5_conviction_low_hit_rate_13w":0.0,"t8_graph_coverage":1.0,"t8_graph_precision_validated_share":1.0,"t5_t5_supply_chain_signals_7d":0.0,"ib_source_share":0.06,"ib_field_coverage_avg":10.5,"equity_curve_points_30d":0,"weekly_issues_report_present":true,"open_p0_issues":0},{"timestamp":"2026-06-20T02:30:02.603296+00:00","T5":617.0,"T8":0.0,"T9":0.0,"t9_branch_count_offmain":58.0,"t5_bearish_sell_today":0.0,"t5_audit_dissent_coverage":1.0,"t5_category_score_coverage":0.9769,"t5_expert_panel_coverage_7d":0.1297,"T6":0.06,"t6_valuation_coverage":0.9769,"T7":0.93,"t8_universe_coverage":96.0,"t8_local_bars_coverage":1.0,"T4":0.0,"t4_avg_holding_days_closed":38.2778,"T10":1.0,"T2":0.0,"t7_t7_earnings_calendar_freshness":0.9062,"VAL":0.0,"t9_backtest_runs_last_28d":19.0,"t9_weekly_reports_with_scorecard":1.0,"t5_t5_weekly_scorecard_present":1.0,"t9_podcast_transcript_validity":0.9676,"t6_annual_report_corpus_tokens":0.3367,"t9_qualitative_signal_coverage":0.4991,"t5_conviction_high_hit_rate_13w":0.0,"t5_conviction_medium_hit_rate_13w":0.0,"t5_conviction_low_hit_rate_13w":0.0,"t8_graph_coverage":1.0,"t8_graph_precision_validated_share":1.0,"t5_t5_supply_chain_signals_7d":0.0,"ib_source_share":0.06,"ib_field_coverage_avg":10.5,"equity_curve_points_30d":0,"weekly_issues_report_present":true,"open_p0_issues":0},{"timestamp":"2026-06-20T06:30:03.149204+00:00","T5":617.0,"T8":0.0,"T9":0.0,"t9_branch_count_offmain":58.0,"t5_bearish_sell_today":0.0,"t5_audit_dissent_coverage":1.0,"t5_category_score_coverage":0.9769,"t5_expert_panel_coverage_7d":0.1297,"T6":0.06,"t6_valuation_coverage":0.9769,"T7":0.93,"t8_universe_coverage":96.0,"t8_local_bars_coverage":1.0,"T4":2.0,"t4_avg_holding_days_closed":38.2778,"T10":1.0,"T2":0.0,"t7_t7_earnings_calendar_freshness":0.9062,"VAL":0.0,"t9_backtest_runs_last_28d":19.0,"t9_weekly_reports_with_scorecard":1.0,"t5_t5_weekly_scorecard_present":1.0,"t9_podcast_transcript_validity":0.9682,"t6_annual_report_corpus_tokens":0.3367,"t9_qualitative_signal_coverage":0.4991,"t5_conviction_high_hit_rate_13w":0.0,"t5_conviction_medium_hit_rate_13w":0.0,"t5_conviction_low_hit_rate_13w":0.0,"t8_graph_coverage":1.0,"t8_graph_precision_validated_share":1.0,"t5_t5_supply_chain_signals_7d":0.0,"ib_source_share":0.06,"ib_field_coverage_avg":10.5,"equity_curve_points_30d":0,"weekly_issues_report_present":true,"open_p0_issues":0},{"timestamp":"2026-06-20T11:00:40.269847+00:00","T5":713.0,"T8":96.0,"T9":0.9062,"t9_branch_count_offmain":58.0,"t5_bearish_sell_today":21.0,"t5_audit_dissent_coverage":1.0,"t5_category_score_coverage":0.98,"t5_expert_panel_coverage_7d":0.2277,"T6":0.06,"t6_valuation_coverage":0.98,"T7":0.93,"t8_universe_coverage":96.0,"t8_local_bars_coverage":1.0,"T4":2.0,"t4_avg_holding_days_closed":38.2778,"T10":1.0,"T2":0.0,"t7_t7_earnings_calendar_freshness":0.9062,"VAL":0.0,"t9_backtest_runs_last_28d":19.0,"t9_weekly_reports_with_scorecard":1.0,"t5_t5_weekly_scorecard_present":1.0,"t9_podcast_transcript_validity":0.9685,"t6_annual_report_corpus_tokens":0.3367,"t9_qualitative_signal_coverage":0.5077,"t5_conviction_high_hit_rate_13w":0.0,"t5_conviction_medium_hit_rate_13w":0.0,"t5_conviction_low_hit_rate_13w":0.0,"t8_graph_coverage":1.0,"t8_graph_precision_validated_share":1.0,"t5_t5_supply_chain_signals_7d":0.0,"ib_source_share":0.06,"ib_field_coverage_avg":10.5,"equity_curve_points_30d":0,"weekly_issues_report_present":true,"open_p0_issues":0},{"timestamp":"2026-06-20T14:00:40.176655+00:00","T5":713.0,"T8":96.0,"T9":0.9062,"t9_branch_count_offmain":58.0,"t5_bearish_sell_today":21.0,"t5_audit_dissent_coverage":1.0,"t5_category_score_coverage":0.98,"t5_expert_panel_coverage_7d":0.2277,"T6":0.06,"t6_valuation_coverage":0.98,"T7":0.93,"t8_universe_coverage":96.0,"t8_local_bars_coverage":1.0,"T4":2.0,"t4_avg_holding_days_closed":38.2778,"T10":1.0,"T2":0.0,"t7_t7_earnings_calendar_freshness":0.9062,"VAL":0.0,"t9_backtest_runs_last_28d":19.0,"t9_weekly_reports_with_scorecard":1.0,"t5_t5_weekly_scorecard_present":1.0,"t9_podcast_transcript_validity":0.9685,"t6_annual_report_corpus_tokens":0.3367,"t9_qualitative_signal_coverage":0.5077,"t5_conviction_high_hit_rate_13w":0.0,"t5_conviction_medium_hit_rate_13w":0.0,"t5_conviction_low_hit_rate_13w":0.0,"t8_graph_coverage":1.0,"t8_graph_precision_validated_share":1.0,"t5_t5_supply_chain_signals_7d":0.0,"ib_source_share":0.06,"ib_field_coverage_avg":10.5,"equity_curve_points_30d":0,"weekly_issues_report_present":true,"open_p0_issues":0},{"timestamp":"2026-06-20T16:30:40.249050+00:00","T5":713.0,"T8":96.0,"T9":0.9062,"t9_branch_count_offmain":58.0,"t5_bearish_sell_today":21.0,"t5_audit_dissent_coverage":1.0,"t5_category_score_coverage":0.98,"t5_expert_panel_coverage_7d":0.2277,"T6":0.06,"t6_valuation_coverage":0.98,"T7":0.93,"t8_universe_coverage":96.0,"t8_local_bars_coverage":1.0,"T4":2.0,"t4_avg_holding_days_closed":38.2778,"T10":1.0,"T2":0.0,"t7_t7_earnings_calendar_freshness":0.9062,"VAL":0.0,"t9_backtest_runs_last_28d":19.0,"t9_weekly_reports_with_scorecard":1.0,"t5_t5_weekly_scorecard_present":1.0,"t9_podcast_transcript_validity":0.9685,"t6_annual_report_corpus_tokens":0.3367,"t9_qualitative_signal_coverage":0.5077,"t5_conviction_high_hit_rate_13w":0.0,"t5_conviction_medium_hit_rate_13w":0.0,"t5_conviction_low_hit_rate_13w":0.0,"t8_graph_coverage":1.0,"t8_graph_precision_validated_share":1.0,"t5_t5_supply_chain_signals_7d":0.0,"ib_source_share":0.06,"ib_field_coverage_avg":10.5,"equity_curve_points_30d":0,"weekly_issues_report_present":true,"open_p0_issues":0},{"timestamp":"2026-06-20T20:00:40.145014+00:00","T5":713.0,"T8":96.0,"T9":0.9062,"t9_branch_count_offmain":58.0,"t5_bearish_sell_today":21.0,"t5_audit_dissent_coverage":1.0,"t5_category_score_coverage":0.98,"t5_expert_panel_coverage_7d":0.2277,"T6":0.06,"t6_valuation_coverage":0.98,"T7":0.93,"t8_universe_coverage":96.0,"t8_local_bars_coverage":1.0,"T4":2.0,"t4_avg_holding_days_closed":38.2778,"T10":1.0,"T2":0.0,"t7_t7_earnings_calendar_freshness":0.9062,"VAL":0.0,"t9_backtest_runs_last_28d":19.0,"t9_weekly_reports_with_scorecard":1.0,"t5_t5_weekly_scorecard_present":1.0,"t9_podcast_transcript_validity":0.9685,"t6_annual_report_corpus_tokens":0.3367,"t9_qualitative_signal_coverage":0.5077,"t5_conviction_high_hit_rate_13w":0.0,"t5_conviction_medium_hit_rate_13w":0.0,"t5_conviction_low_hit_rate_13w":0.0,"t8_graph_coverage":1.0,"t8_graph_precision_validated_share":1.0,"t5_t5_supply_chain_signals_7d":0.0,"ib_source_share":0.06,"ib_field_coverage_avg":10.5,"equity_curve_points_30d":0,"weekly_issues_report_present":true,"open_p0_issues":0},{"timestamp":"2026-06-21T02:30:40.231430+00:00","T5":713.0,"T8":0.0,"T9":0.0,"t9_branch_count_offmain":58.0,"t5_bearish_sell_today":0.0,"t5_audit_dissent_coverage":1.0,"t5_category_score_coverage":0.98,"t5_expert_panel_coverage_7d":0.2277,"T6":0.06,"t6_valuation_coverage":0.98,"T7":0.93,"t8_universe_coverage":96.0,"t8_local_bars_coverage":1.0,"T4":2.0,"t4_avg_holding_days_closed":38.2778,"T10":1.0,"T2":0.0,"t7_t7_earnings_calendar_freshness":0.0417,"VAL":0.0,"t9_backtest_runs_last_28d":19.0,"t9_weekly_reports_with_scorecard":1.0,"t5_t5_weekly_scorecard_present":1.0,"t9_podcast_transcript_validity":0.9686,"t6_annual_report_corpus_tokens":0.3367,"t9_qualitative_signal_coverage":0.5077,"t5_conviction_high_hit_rate_13w":0.0,"t5_conviction_medium_hit_rate_13w":0.0,"t5_conviction_low_hit_rate_13w":0.0,"t8_graph_coverage":1.0,"t8_graph_precision_validated_share":1.0,"t5_t5_supply_chain_signals_7d":0.0,"ib_source_share":0.06,"ib_field_coverage_avg":10.5,"equity_curve_points_30d":0,"weekly_issues_report_present":true,"open_p0_issues":0},{"timestamp":"2026-06-21T06:30:40.628323+00:00","T5":617.0,"T8":0.0,"T9":0.0,"t9_branch_count_offmain":58.0,"t5_bearish_sell_today":0.0,"t5_audit_dissent_coverage":1.0,"t5_category_score_coverage":0.9769,"t5_expert_panel_coverage_7d":0.2629,"T6":0.06,"t6_valuation_coverage":0.9769,"T7":0.93,"t8_universe_coverage":96.0,"t8_local_bars_coverage":1.0,"T4":2.0,"t4_avg_holding_days_closed":38.2778,"T10":1.0,"T2":0.0,"t7_t7_earnings_calendar_freshness":0.0417,"VAL":0.0,"t9_backtest_runs_last_28d":19.0,"t9_weekly_reports_with_scorecard":1.0,"t5_t5_weekly_scorecard_present":1.0,"t9_podcast_transcript_validity":0.9686,"t6_annual_report_corpus_tokens":0.3367,"t9_qualitative_signal_coverage":0.5027,"t5_conviction_high_hit_rate_13w":0.0,"t5_conviction_medium_hit_rate_13w":0.0,"t5_conviction_low_hit_rate_13w":0.0,"t8_graph_coverage":1.0,"t8_graph_precision_validated_share":1.0,"t5_t5_supply_chain_signals_7d":0.0,"ib_source_share":0.06,"ib_field_coverage_avg":10.5,"equity_curve_points_30d":0,"weekly_issues_report_present":true,"open_p0_issues":0},{"timestamp":"2026-06-21T11:00:40.133983+00:00","T5":713.0,"T8":96.0,"T9":0.9062,"t9_branch_count_offmain":58.0,"t5_bearish_sell_today":21.0,"t5_audit_dissent_coverage":1.0,"t5_category_score_coverage":0.98,"t5_expert_panel_coverage_7d":0.3446,"T6":0.06,"t6_valuation_coverage":0.98,"T7":0.93,"t8_universe_coverage":96.0,"t8_local_bars_coverage":1.0,"T4":2.0,"t4_avg_holding_days_closed":38.2778,"T10":1.0,"T2":0.0,"t7_t7_earnings_calendar_freshness":1.0,"VAL":0.0,"t9_backtest_runs_last_28d":19.0,"t9_weekly_reports_with_scorecard":1.0,"t5_t5_weekly_scorecard_present":1.0,"t9_podcast_transcript_validity":0.9686,"t5_t5_action_type_coverage":0.2677,"t6_annual_report_corpus_tokens":0.3367,"t9_qualitative_signal_coverage":0.5108,"t5_conviction_high_hit_rate_13w":0.0,"t5_conviction_medium_hit_rate_13w":0.0,"t5_conviction_low_hit_rate_13w":0.0,"t8_graph_coverage":1.0,"t8_graph_precision_validated_share":1.0,"t5_t5_supply_chain_signals_7d":0.0,"ib_source_share":0.06,"ib_field_coverage_avg":10.5,"equity_curve_points_30d":0,"weekly_issues_report_present":true,"open_p0_issues":0},{"timestamp":"2026-06-21T14:00:40.131283+00:00","T5":713.0,"T8":96.0,"T9":0.9062,"t9_branch_count_offmain":58.0,"t5_bearish_sell_today":21.0,"t5_audit_dissent_coverage":1.0,"t5_category_score_coverage":0.98,"t5_expert_panel_coverage_7d":0.3446,"T6":0.06,"t6_valuation_coverage":0.98,"T7":0.93,"t8_universe_coverage":96.0,"t8_local_bars_coverage":1.0,"T4":2.0,"t4_avg_holding_days_closed":38.2778,"T10":1.0,"T2":0.0,"t7_t7_earnings_calendar_freshness":1.0,"VAL":0.0,"t9_backtest_runs_last_28d":19.0,"t9_weekly_reports_with_scorecard":1.0,"t5_t5_weekly_scorecard_present":1.0,"t9_podcast_transcript_validity":0.9686,"t5_t5_action_type_coverage":0.2677,"t6_annual_report_corpus_tokens":0.3367,"t9_qualitative_signal_coverage":0.5108,"t5_conviction_high_hit_rate_13w":0.0,"t5_conviction_medium_hit_rate_13w":0.0,"t5_conviction_low_hit_rate_13w":0.0,"t8_graph_coverage":1.0,"t8_graph_precision_validated_share":1.0,"t5_t5_supply_chain_signals_7d":0.0,"ib_source_share":0.06,"ib_field_coverage_avg":10.5,"equity_curve_points_30d":0,"weekly_issues_report_present":true,"open_p0_issues":0},{"timestamp":"2026-06-21T16:30:40.210563+00:00","T5":713.0,"T8":96.0,"T9":0.9062,"t9_branch_count_offmain":58.0,"t5_bearish_sell_today":21.0,"t5_audit_dissent_coverage":1.0,"t5_category_score_coverage":0.98,"t5_expert_panel_coverage_7d":0.3446,"T6":0.06,"t6_valuation_coverage":0.98,"T7":0.93,"t8_universe_coverage":96.0,"t8_local_bars_coverage":1.0,"T4":2.0,"t4_avg_holding_days_closed":38.2778,"T10":1.0,"T2":0.0,"t7_t7_earnings_calendar_freshness":1.0,"VAL":0.0,"t9_backtest_runs_last_28d":19.0,"t9_weekly_reports_with_scorecard":1.0,"t5_t5_weekly_scorecard_present":1.0,"t9_podcast_transcript_validity":0.9686,"t5_t5_action_type_coverage":0.2677,"t6_annual_report_corpus_tokens":0.3367,"t9_qualitative_signal_coverage":0.5108,"t5_conviction_high_hit_rate_13w":0.0,"t5_conviction_medium_hit_rate_13w":0.0,"t5_conviction_low_hit_rate_13w":0.0,"t8_graph_coverage":1.0,"t8_graph_precision_validated_share":1.0,"t5_t5_supply_chain_signals_7d":0.0,"ib_source_share":0.06,"ib_field_coverage_avg":10.5,"equity_curve_points_30d":0,"weekly_issues_report_present":true,"open_p0_issues":0},{"timestamp":"2026-06-21T20:00:40.141805+00:00","T5":713.0,"T8":96.0,"T9":0.9062,"t9_branch_count_offmain":69.0,"t5_bearish_sell_today":21.0,"t5_audit_dissent_coverage":1.0,"t5_category_score_coverage":0.98,"t5_expert_panel_coverage_7d":0.3446,"T6":0.06,"t6_valuation_coverage":0.98,"T7":0.93,"t8_universe_coverage":96.0,"t8_local_bars_coverage":1.0,"T4":2.0,"t4_avg_holding_days_closed":38.2778,"T10":1.0,"T2":0.0,"t7_t7_earnings_calendar_freshness":1.0,"VAL":0.0,"t9_backtest_runs_last_28d":19.0,"t9_weekly_reports_with_scorecard":1.0,"t5_t5_weekly_scorecard_present":1.0,"t9_podcast_transcript_validity":0.9686,"t5_t5_action_type_coverage":0.2677,"t6_annual_report_corpus_tokens":0.3367,"t9_qualitative_signal_coverage":0.5108,"t5_conviction_high_hit_rate_13w":0.0,"t5_conviction_medium_hit_rate_13w":0.0,"t5_conviction_low_hit_rate_13w":0.0,"t8_graph_coverage":1.0,"t8_graph_precision_validated_share":1.0,"t5_t5_supply_chain_signals_7d":0.0,"ib_source_share":0.06,"ib_field_coverage_avg":10.5,"equity_curve_points_30d":0,"weekly_issues_report_present":true,"open_p0_issues":0},{"timestamp":"2026-06-21T20:20:44.532941+00:00","T5":713.0,"T8":96.0,"T9":1.0,"t9_branch_count_offmain":69.0,"t5_bearish_sell_today":21.0,"t5_audit_dissent_coverage":1.0,"t5_category_score_coverage":0.98,"t5_expert_panel_coverage_7d":0.3446,"T6":0.06,"t6_valuation_coverage":0.98,"T7":0.93,"t8_universe_coverage":96.0,"t8_local_bars_coverage":1.0,"T4":2.0,"t4_avg_holding_days_closed":38.2778,"T10":1.0,"T2":0.0,"t7_t7_earnings_calendar_freshness":1.0,"VAL":0.0,"t9_backtest_runs_last_28d":19.0,"t9_weekly_reports_with_scorecard":1.0,"t5_t5_weekly_scorecard_present":1.0,"t9_podcast_transcript_validity":0.9686,"t5_t5_action_type_coverage":0.2677,"t6_annual_report_corpus_tokens":0.3367,"t9_qualitative_signal_coverage":0.5108,"t5_conviction_high_hit_rate_13w":0.0,"t5_conviction_medium_hit_rate_13w":0.0,"t5_conviction_low_hit_rate_13w":0.0,"t8_graph_coverage":1.0,"t8_graph_precision_validated_share":1.0,"t5_t5_supply_chain_signals_7d":0.0,"ib_source_share":0.06,"ib_field_coverage_avg":10.5,"equity_curve_points_30d":0,"weekly_issues_report_present":true,"open_p0_issues":0},{"timestamp":"2026-06-22T02:30:40.190261+00:00","T5":713.0,"T8":0.0,"T9":0.0,"t9_branch_count_offmain":69.0,"t5_bearish_sell_today":0.0,"t5_audit_dissent_coverage":1.0,"t5_category_score_coverage":0.98,"t5_expert_panel_coverage_7d":0.3446,"T6":0.06,"t6_valuation_coverage":0.98,"T7":0.93,"t8_universe_coverage":96.0,"t8_local_bars_coverage":0.0,"T4":2.0,"t4_avg_holding_days_closed":38.2778,"T10":1.0,"T2":0.0,"t7_t7_earnings_calendar_freshness":1.0,"VAL":0.0,"t9_backtest_runs_last_28d":19.0,"t9_weekly_reports_with_scorecard":1.0,"t5_t5_weekly_scorecard_present":0.0,"t9_podcast_transcript_validity":0.9689,"t5_t5_action_type_coverage":0.2677,"t6_annual_report_corpus_tokens":0.3367,"t9_qualitative_signal_coverage":0.5108,"t5_conviction_high_hit_rate_13w":0.0,"t5_conviction_medium_hit_rate_13w":0.0,"t5_conviction_low_hit_rate_13w":0.0,"t8_graph_coverage":1.0,"t8_graph_precision_validated_share":1.0,"t5_t5_supply_chain_signals_7d":0.0,"ib_source_share":0.06,"ib_field_coverage_avg":10.5,"equity_curve_points_30d":0,"weekly_issues_report_present":false,"open_p0_issues":0},{"timestamp":"2026-06-22T06:30:40.625325+00:00","T5":617.0,"T8":0.0,"T9":0.0,"t9_branch_count_offmain":69.0,"t5_bearish_sell_today":0.0,"t5_audit_dissent_coverage":1.0,"t5_category_score_coverage":0.9822,"t5_expert_panel_coverage_7d":0.3979,"T6":0.06,"t6_valuation_coverage":0.9822,"T7":0.93,"t8_universe_coverage":96.0,"t8_local_bars_coverage":0.0,"T4":2.0,"t4_avg_holding_days_closed":38.2778,"T10":1.0,"T2":0.0,"t7_t7_earnings_calendar_freshness":1.0,"VAL":0.0,"t9_backtest_runs_last_28d":19.0,"t9_weekly_reports_with_scorecard":1.0,"t5_t5_weekly_scorecard_present":0.0,"t9_podcast_transcript_validity":0.9689,"t5_t5_action_type_coverage":0.3091,"t6_annual_report_corpus_tokens":0.3367,"t9_qualitative_signal_coverage":0.508,"t5_conviction_high_hit_rate_13w":0.0,"t5_conviction_medium_hit_rate_13w":0.0,"t5_conviction_low_hit_rate_13w":0.0,"t8_graph_coverage":1.0,"t8_graph_precision_validated_share":1.0,"t5_t5_supply_chain_signals_7d":0.0,"ib_source_share":0.06,"ib_field_coverage_avg":10.5,"equity_curve_points_30d":0,"weekly_issues_report_present":false,"open_p0_issues":0},{"timestamp":"2026-06-22T11:00:40.590261+00:00","T5":723.0,"T8":96.0,"T9":1.0,"t9_branch_count_offmain":69.0,"t5_bearish_sell_today":25.0,"t5_audit_dissent_coverage":1.0,"t5_category_score_coverage":0.9773,"t5_expert_panel_coverage_7d":0.4515,"T6":0.06,"t6_valuation_coverage":0.9773,"T7":0.93,"t8_universe_coverage":96.0,"t8_local_bars_coverage":0.9896,"T4":2.0,"t4_avg_holding_days_closed":39.4762,"T10":1.0,"T2":0.0,"t7_t7_earnings_calendar_freshness":1.0,"VAL":0.0,"t9_backtest_runs_last_28d":20.0,"t9_weekly_reports_with_scorecard":1.0,"t5_t5_weekly_scorecard_present":1.0,"t9_podcast_transcript_validity":0.9689,"t5_t5_action_type_coverage":0.4106,"t6_annual_report_corpus_tokens":0.3367,"t9_qualitative_signal_coverage":0.5061,"t5_conviction_high_hit_rate_13w":0.0,"t5_conviction_medium_hit_rate_13w":0.0,"t5_conviction_low_hit_rate_13w":0.0,"t8_graph_coverage":1.0,"t8_graph_precision_validated_share":1.0,"t5_t5_supply_chain_signals_7d":0.0,"ib_source_share":0.06,"ib_field_coverage_avg":10.5,"equity_curve_points_30d":0,"weekly_issues_report_present":true,"open_p0_issues":0},{"timestamp":"2026-06-26T16:30:02.685518+00:00","T5":403.0,"T8":96.0,"T9":1.0,"t9_branch_count_offmain":69.0,"t5_bearish_sell_today":26.0,"t5_audit_dissent_coverage":1.0,"t5_category_score_coverage":0.9728,"t5_expert_panel_coverage_7d":0.8093,"T6":0.06,"t6_valuation_coverage":0.9728,"T7":0.93,"t8_universe_coverage":96.0,"t8_local_bars_coverage":1.0,"T4":2.0,"t4_avg_holding_days_closed":41.6667,"T10":1.0,"T2":0.0,"t7_t7_earnings_calendar_freshness":1.0,"VAL":0.0,"t9_backtest_runs_last_28d":20.0,"t9_weekly_reports_with_scorecard":1.0,"t5_t5_weekly_scorecard_present":1.0,"t9_podcast_transcript_validity":0.9694,"t5_t5_action_type_coverage":1.0,"t6_annual_report_corpus_tokens":0.3367,"t9_qualitative_signal_coverage":0.5259,"t5_conviction_high_hit_rate_13w":0.0,"t5_conviction_medium_hit_rate_13w":0.0,"t5_conviction_low_hit_rate_13w":0.0,"t8_graph_coverage":1.0,"t8_graph_precision_validated_share":1.0,"t5_t5_supply_chain_signals_7d":0.0,"ib_source_share":0.06,"ib_field_coverage_avg":10.5,"equity_curve_points_30d":0,"weekly_issues_report_present":true,"open_p0_issues":0},{"timestamp":"2026-06-26T20:00:42.934309+00:00","T5":403.0,"T8":96.0,"T9":1.0,"t9_branch_count_offmain":69.0,"t5_bearish_sell_today":26.0,"t5_audit_dissent_coverage":1.0,"t5_category_score_coverage":0.9728,"t5_expert_panel_coverage_7d":0.8093,"T6":0.06,"t6_valuation_coverage":0.9728,"T7":0.9789,"t8_universe_coverage":96.0,"t8_local_bars_coverage":1.0,"T4":2.0,"t4_avg_holding_days_closed":41.6667,"T10":1.0,"T2":0.0,"t7_t7_earnings_calendar_freshness":1.0,"VAL":0.0,"t9_backtest_runs_last_28d":20.0,"t9_weekly_reports_with_scorecard":1.0,"t5_t5_weekly_scorecard_present":1.0,"t9_podcast_transcript_validity":0.9696,"t5_t5_action_type_coverage":1.0,"t6_annual_report_corpus_tokens":0.3367,"t9_qualitative_signal_coverage":0.5259,"t5_conviction_high_hit_rate_13w":0.0,"t5_conviction_medium_hit_rate_13w":0.0,"t5_conviction_low_hit_rate_13w":0.0,"t8_graph_coverage":1.0,"t8_graph_precision_validated_share":1.0,"t5_t5_supply_chain_signals_7d":0.0,"ib_source_share":0.06,"ib_field_coverage_avg":10.5,"equity_curve_points_30d":0,"weekly_issues_report_present":true,"open_p0_issues":0},{"timestamp":"2026-06-27T02:30:43.593504+00:00","T5":403.0,"T8":0.0,"T9":0.0,"t9_branch_count_offmain":69.0,"t5_bearish_sell_today":0.0,"t5_audit_dissent_coverage":1.0,"t5_category_score_coverage":0.9728,"t5_expert_panel_coverage_7d":0.8093,"T6":0.06,"t6_valuation_coverage":0.9728,"T7":0.9789,"t8_universe_coverage":96.0,"t8_local_bars_coverage":1.0,"T4":2.0,"t4_avg_holding_days_closed":41.6667,"T10":1.0,"T2":0.0,"t7_t7_earnings_calendar_freshness":1.0,"VAL":0.0,"t9_backtest_runs_last_28d":20.0,"t9_weekly_reports_with_scorecard":1.0,"t5_t5_weekly_scorecard_present":1.0,"t9_podcast_transcript_validity":0.9702,"t5_t5_action_type_coverage":1.0,"t6_annual_report_corpus_tokens":0.3367,"t9_qualitative_signal_coverage":0.5259,"t5_conviction_high_hit_rate_13w":0.0,"t5_conviction_medium_hit_rate_13w":0.0,"t5_conviction_low_hit_rate_13w":0.0,"t5_t5_outcome_resolution_backlog":226.0,"t8_graph_coverage":1.0,"t8_graph_precision_validated_share":1.0,"t5_t5_supply_chain_signals_7d":0.0,"t5_t5_avanza_owner_signals_7d":0.0,"ib_source_share":0.06,"ib_field_coverage_avg":10.5,"equity_curve_points_30d":0,"weekly_issues_report_present":true,"open_p0_issues":0},{"timestamp":"2026-06-27T06:30:43.417076+00:00","T5":629.0,"T8":0.0,"T9":0.0,"t9_branch_count_offmain":69.0,"t5_bearish_sell_today":0.0,"t5_audit_dissent_coverage":1.0,"t5_category_score_coverage":0.9728,"t5_expert_panel_coverage_7d":0.8093,"T6":0.06,"t6_valuation_coverage":0.9728,"T7":0.9789,"t8_universe_coverage":96.0,"t8_local_bars_coverage":1.0,"T4":2.0,"t4_avg_holding_days_closed":41.6667,"T10":1.0,"T2":0.0,"t7_t7_earnings_calendar_freshness":1.0,"VAL":0.0,"t9_backtest_runs_last_28d":20.0,"t9_weekly_reports_with_scorecard":1.0,"t5_t5_weekly_scorecard_present":1.0,"t9_podcast_transcript_validity":0.9714,"t5_t5_action_type_coverage":1.0,"t6_annual_report_corpus_tokens":0.3367,"t9_qualitative_signal_coverage":0.5259,"t5_conviction_high_hit_rate_13w":0.054,"t5_conviction_medium_hit_rate_13w":0.0,"t5_conviction_low_hit_rate_13w":0.0,"t5_conformal_calibration_coverage":0.907,"t5_t5_outcome_resolution_backlog":0.0,"t8_graph_coverage":1.0,"t8_graph_precision_validated_share":1.0,"t5_t5_supply_chain_signals_7d":0.0,"t5_t5_avanza_owner_signals_7d":0.0,"ib_source_share":0.06,"ib_field_coverage_avg":10.5,"equity_curve_points_30d":0,"weekly_issues_report_present":true,"open_p0_issues":0}]